Workbook

Sheet Decreased
A1: Score_iNC
A2: <=16%
A3: 45911.476 | B3: October | C3: Ospina, Michel | D3: mospin@ext.uber.com | E3: ACCM | G3: agente | I3: 5 | J3: 5 | K3: 1_Stars_Percentage | L3: < | M3: 34 | N3: 34
A4: 45924.498 | B4: October | C4: Ospina, Michel | D4: mospin@ext.uber.com | E4: ACCM | F4: Latam Eater Ring Fence | G4: agente | I4: 30 | J4: 30 | K4: 1_Stars_Percentage | L4: < | M4: 34 | N4: 34
A5: 45925.47 | B5: October | C5: Ospina, Michel | D5: mospin@ext.uber.com | E5: ACCM | F5: LatAm U4B Triage | G5: agente | I5: 30 | J5: 30 | K5: ABS Injus | L5: < | M5: 50 | N5: 50
A6: 45925.47 | B6: October | C6: Ospina, Michel | D6: mospin@ext.uber.com | E6: ACCM | F6: LatAm U4B Triage | G6: agente | I6: 30 | J6: 30 | K6: Quality@Uber | L6: < | M6: 10 | N6: 10
A7: 45925.49 | B7: October | C7: Ospina, Michel | D7: mospin@ext.uber.com | E7: ACCM | F7: US Spa Earner Acc/Pay | G7: agente | I7: 5 | J7: 5 | K7: 1_Stars_Percentage | L7: < | M7: 34 | N7: 34
A8: 45925.497 | B8: October | C8: Ospina, Michel | D8: mospin@ext.uber.com | E8: ACCM | G8: agente | I8: 30 | J8: 30 | K8: 1_Stars_Percentage | L8: <= | M8: 50 | N8: 50

Sheet Resultados
A1: BMS ID | B1: Nombre | C1: LOB | D1: Mes | E1: Salario | F1: Salario Personalizado | G1: Total Keys | H1: Total Bonus | I1: Total Additional | J1: Total Decreased | K1: Total General | L1: Razón Cero | M1: Fecha Cálculo
A2: 2116682 | B2: Pinzon, Cindy - 6682 | C2: US Spa Earner Acc/Pay | D2: 1 | E2: 1600000 | F2: NO | G2: 0 | H2: 0 | I2: 0 | J2: 0 | K2: 0 | M2: 46046.843
A3: 2816053 | B3: Castaneda, Maria - 6053 | C3: US Spa Earner Acc/Pay | D3: 1 | E3: 1600000 | F3: NO | G3: 0 | H3: 0 | I3: 0 | J3: 0 | K3: 0 | M3: 46046.843
A4: 3195695 | B4: MartinezS, Sebastian - 5695 | C4: US Spa Earner Acc/Pay | D4: 1 | E4: 1600000 | F4: NO | G4: 0 | H4: 0 | I4: 0 | J4: 0 | K4: 0 | M4: 46046.843
A5: 3460648 | B5: Villada, Maria - 0648 | C5: US Spa Earner Acc/Pay | D5: 1 | E5: 1600000 | F5: NO | G5: 0 | H5: 0 | I5: 0 | J5: 0 | K5: 0 | M5: 46046.843
A6: 3524085 | B6: Gomez, Patricia - 4085 | C6: US Spa Earner Acc/Pay | D6: 1 | E6: 1600000 | F6: NO | G6: 0 | H6: 0 | I6: 0 | J6: 0 | K6: 0 | M6: 46046.843
A7: 3570218 | B7: Gomez, Erik - 0218 | C7: US Spa Earner Acc/Pay | D7: 1 | E7: 1600000 | F7: NO | G7: 0 | H7: 0 | I7: 0 | J7: 0 | K7: 0 | M7: 46046.843
A8: 3924273 | B8: Espitia, Margy - 4273 | C8: US Spa Earner Acc/Pay | D8: 1 | E8: 1600000 | F8: NO | G8: 0 | H8: 0 | I8: 0 | J8: 0 | K8: 0 | M8: 46046.843
A9: 4734515 | B9: Guerra, Pablo - 4515 | C9: US Spa Earner Acc/Pay | D9: 1 | E9: 1600000 | F9: NO | G9: 0 | H9: 0 | I9: 0 | J9: 0 | K9: 0 | M9: 46046.843
A10: 4747160 | B10: DiazV, Nicolas - 7160 | C10: US Spa Earner Acc/Pay | D10: 1 | E10: 1600000 | F10: NO | G10: 0 | H10: 0 | I10: 0 | J10: 0 | K10: 0 | M10: 46046.843
A11: 5021467 | B11: Ortega, Ana - 1467 | C11: US Spa Earner Acc/Pay | D11: 1 | E11: 1600000 | F11: NO | G11: 0 | H11: 0 | I11: 0 | J11: 0 | K11: 0 | M11: 46046.843
A12: 5021481 | B12: Camacho, Danna - 1481 | C12: US Spa Earner Acc/Pay | D12: 1 | E12: 1600000 | F12: NO | G12: 0 | H12: 0 | I12: 0 | J12: 0 | K12: 0 | M12: 46046.843
A13: 5031967 | B13: Omana, Juan - 1967 | C13: US Spa Earner Acc/Pay | D13: 1 | E13: 1600000 | F13: NO | G13: 0 | H13: 0 | I13: 0 | J13: 0 | K13: 0 | M13: 46046.843
... A44: 5651748 | B44: Garzon, Maria Del Mar - 1748 | C44: US Spa Earner Acc/Pay | D44: 1 | E44: 1600000 | F44: NO | G44: 0 | H44: 0 | I44: 0 | J44: 0 | K44: 0 | M44: 46046.843
A45: TOTAL LOB | C45: US Spa Earner Acc/Pay | D45: 1 | K45: 0 | M45: 46046.843

Sheet Audit_Log
A1: Timestamp | B1: Tipo Acción | C1: Usuario | D1: BMS ID | E1: Nombre | F1: LOB | G1: Decisión | H1: Detalles
A2: 45979.75 | B2: Respuesta Disputa | C2: mikenet11@gmail.com | D2: 5546192 | E2: Cortes, Daniel - 6192 | F2: US Cross Support | G2: RECHAZADA | H2: werwerwer
A3: 45979.754 | B3: Respuesta Disputa | C3: mikenet11@gmail.com | D3: 5320995 | E3: Zamorano, Kevin - 0995 | F3: US Cross Support | G3: APROBADA | H3: sdfsdfsdfsdf
A4: 45990.825 | B4: Respuesta Disputa | C4: mikenet11@gmail.com | D4: 2164860 | E4: Sanchez, Karen - 4860 | F4: US Cross Support | G4: RECHAZADA | H4: werwer

Sheet Disputa_Respuestas
A1: ID Disputa | B1: BMS ID | C1: Nombre | D1: LOB | E1: Fecha Disputa | F1: Estado Original | G1: Estado Nuevo | H1: Respuesta | I1: Decisión | J1: Monto Ajustado | K1: Usuario Responde | L1: Fecha Respuesta | M1: Comentario Interno
A2: 9 | B2: 5546192 | C2: Cortes, Daniel - 6192 | D2: US Cross Support | E2: 2025-11-06T16:46:27.687Z | F2: Pendiente | G2: ❌ Rechazada | H2: werwerwer | I2: RECHAZADA | J2: 0 | K2: mikenet11@gmail.com | L2: 45979.75 | M2: werwerwer
A3: 3 | B3: 5320995 | C3: Zamorano, Kevin - 0995 | D3: US Spa Earner Acc/Pay | E3: 2025-11-05T03:18:39.141Z | F3: Pendiente | G3: ✅ Aprobada | H3: sdfsdfsdfsdf | I3: APROBADA | J3: 100000000 | K3: mikenet11@gmail.com | L3: 45979.754 | M3: miekangelo
A4: 8 | B4: 2164860 | C4: Sanchez, Karen - 4860 | D4: US Cross Support | E4: 2025-11-06T16:44:53.916Z | F4: Pendiente | G4: ❌ Rechazada | H4: werwer | I4: RECHAZADA | J4: 0 | K4: mikenet11@gmail.com | L4: 45990.825 | M4: werwer

Sheet Ajustes_Traslados
A1: Fecha Traslado | B1: Fecha HC | C1: Mes CDM | D1: BMS ID | E1: Nombre | F1: LOB Anterior | G1: LOB Nueva | H1: Usuario | I1: Nota
A2: 45970.734 | B2: Enero | C2: 1 | D2: 4364806 | E2: SanchezC, Natalia - 4806 | F2: US Cross Support | G2: Eats Phone US LO | H2: mikenet11@gmail.com | I2: Traslado temporal
A3: 45970.734 | B3: Enero | C3: 1 | D3: 5321000 | E3: Fuertes, Onedis - 1000 | F3: US Cross Support | G3: Eats Phone US LO | H3: mikenet11@gmail.com | I3: Traslado temporal
A4: 45988.774 | B4: Enero | C4: 1 | D4: 5321006 | E4: Zerpa, Leonardo - 1006 | F4: US Cross Support | G4: US Spa Earner Acc/Pay | H4: mikenet11@gmail.com | I4: Traslado temporal
A5: 45988.774 | B5: Enero | C5: 1 | D5: 5546192 | E5: Cortes, Daniel - 6192 | F5: US Cross Support | G5: US Spa Consumer ACC | H5: mikenet11@gmail.com | I5: Traslado temporal
A6: 45990.807 | B6: Enero | C6: 1 | D6: 5651744 | E6: Ramirez, Erika - 1744 | F6: US Cross Support | G6: US Spa Earner Acc/Pay | H6: mikenet11@gmail.com | I6: Traslado temporal
A7: 45990.807 | B7: Enero | C7: 1 | D7: 5086059 | E7: Caceres, Sara - 6059 | F7: US Cross Support | G7: US Phone Earner Priority | H7: mikenet11@gmail.com | I7: Traslado temporal
A8: 46033.403 | B8: Enero | C8: 1 | D8: 3628777 | E8: Pinto, Laura - 8777 | F8: US Phone Earner Diamond | G8: US Phone Eng VS | H8: mikenet11@gmail.com | I8: Traslado temporal

Sheet Traslados_Temporales
A1: Fecha Traslado | B1: BMS ID | C1: Nombre | D1: LOB Original | E1: LOB Destino | F1: Fecha KPI | G1: Mes CDM | H1: Usuario | I1: Estado | J1: Fecha Fin

Sheet Ajustes_Recalculo
A1: Fecha Registro | B1: BMS ID | C1: Nombre | D1: LOB Original | E1: LOB Cálculo | F1: Fecha HC | G1: Mes CDM | H1: Usuario
A2: 45968.818 | B2: 5388841 | C2: Guzman, Paula - 8841 | D2: US Cross Support | E2: US Spa Earner Acc/Pay | F2: Enero | G2: 1 | H2: mikenet11@gmail.com
A3: 45969.252 | B3: 5546192 | C3: Cortes, Daniel - 6192 | D3: US Cross Support | E3: US Spa Consumer ACC | F3: Enero | G3: 1 | H3: mikenet11@gmail.com

Sheet Incentivos_Participantes
A1: Fecha Registro | B1: Fecha KPI | C1: KPI | D1: BMS ID | E1: Nombre | F1: LOB | G1: Bono | H1: Posición | I1: Estado
A2: 45970.724 | B2: Enero | C2: 1_Stars_Percentage | D2: 5388841 | E2: Guzman, Paula - 8841 | F2: US Cross Support | G2: 194820.12 | H2: 1 | I2: Participante
A3: 45970.724 | B3: Enero | C3: 1_Stars_Percentage | D3: 2644855 | E3: Gomez, Luisa - 4855 | F3: US Cross Support | G3: 194820.12 | H3: 2 | I3: Participante
A4: 45970.724 | B4: Enero | C4: 1_Stars_Percentage | D4: 5360362 | E4: Puentes, Anderson - 0362 | F4: US Cross Support | G4: 194820.12 | H4: 3 | I4: Participante
A5: 45970.724 | B5: Enero | C5: 1_Stars_Percentage | D5: 2816053 | E5: Castaneda, Maria - 6053 | F5: US Spa Earner Acc/Pay | G5: 146115.09 | H5: 4 | I5: Participante

Sheet Additional Incentive
A1: KPI_INC_1
A2: TOAST
A3: 45925.471 | B3: October | C3: Ospina, Michel | D3: mospin@ext.uber.com | E3: ACCM | F3: LatAm U4B Triage | G3: agente | I3: 30 | J3: 30 | K3: SHK TK | L3: < | M3: 100 | N3: 100
A4: 45925.48 | B4: October | C4: Ospina, Michel | D4: mospin@ext.uber.com | E4: ACCM | G4: agente | I4: 5 | J4: 5 | K4: 1_Stars_Percentage | L4: < | M4: 34 | N4: 34
A5: 45925.493 | B5: October | C5: Ospina, Michel | D5: mospin@ext.uber.com | E5: ACCM | G5: agente | I5: 5 | J5: 5 | K5: 1_Stars_Percentage | L5: < | M5: 78 | N5: 78
A6: 45925.495 | B6: October | C6: Ospina, Michel | D6: mospin@ext.uber.com | E6: ACCM | G6: agente | I6: 30 | J6: 30 | K6: 1_Stars_Percentage | L6: < | M6: 78 | N6: 78
A7: 45925.495 | B7: October | C7: Ospina, Michel | D7: mospin@ext.uber.com | E7: ACCM | G7: agente | I7: 30 | J7: 30 | K7: 1_Stars_Percentage | L7: < | M7: 78 | N7: 78
A8: 45925.495 | B8: October | C8: Ospina, Michel | D8: mospin@ext.uber.com | E8: ACCM | G8: agente | I8: 30 | J8: 30 | K8: 1_Stars_Percentage | L8: < | M8: 50 | N8: 50
A9: 45925.497 | B9: October | C9: Ospina, Michel | D9: mospin@ext.uber.com | E9: ACCM | G9: agente | I9: 30 | J9: 30 | K9: TPH | L9: < | M9: 30 | N9: 30
A10: 45925.642 | B10: October | C10: Ospina, Michel | D10: mospin@ext.uber.com | E10: ACCM | F10: US Spa Earner Acc/Pay | G10: agente | I10: 30 | J10: 30 | K10: SHK TK | L10: < | M10: 20 | N10: 20
A11: 45925.645 | B11: October | C11: Ospina, Michel | D11: mospin@ext.uber.com | E11: ACCM | G11: agente | I11: 30 | J11: 30 | K11: 1_Stars_Percentage | L11: < | M11: 20 | N11: 20
A12: 45925.646 | B12: October | C12: Ospina, Michel | D12: mospin@ext.uber.com | E12: ACCM | G12: agente | I12: 30 | J12: 30 | K12: 1_Stars_Percentage | L12: < | M12: 20 | N12: 20
A13: 45925.647 | B13: October | C13: Ospina, Michel | D13: mospin@ext.uber.com | E13: ACCM | F13: US Spa Earner Acc/Pay | G13: agente | I13: 30 | J13: 30 | K13: 1_Stars_Percentage | L13: < | M13: 20 | N13: 20
A14: 45925.655 | B14: October | C14: Ospina, Michel | D14: mospin@ext.uber.com | E14: ACCM | F14: US Spa Earner Acc/Pay | G14: agente | I14: 30 | J14: 30 | K14: 1_Stars_Percentage | L14: < | M14: 20 | N14: 20
A15: 45925.655 | B15: October | C15: Ospina, Michel | D15: mospin@ext.uber.com | E15: ACCM | F15: US Spa Earner Acc/Pay | G15: agente | I15: 30 | J15: 30 | K15: 1_Stars_Percentage | L15: < | M15: 20 | N15: 20
A16: 45925.656 | B16: October | C16: Ospina, Michel | D16: mospin@ext.uber.com | E16: ACCM | F16: US Spa Earner Acc/Pay | G16: agente | I16: 5 | J16: 5 | K16: 1_Stars_Percentage | L16: < | M16: 23 | N16: 23
A17: 45925.657 | B17: October | C17: Ospina, Michel | D17: mospin@ext.uber.com | E17: ACCM | F17: US Spa Earner Acc/Pay | G17: agente | I17: 30 | J17: 30 | K17: 1_Stars_Percentage | L17: < | M17: 23 | N17: 23
A18: 45925.657 | B18: October | C18: Ospina, Michel | D18: mospin@ext.uber.com | E18: ACCM | F18: US Spa Earner Acc/Pay | G18: agente | I18: 30 | J18: 30 | K18: 1_Stars_Percentage | L18: < | M18: 20 | N18: 20
A19: 45925.661 | B19: October | C19: Ospina, Michel | D19: mospin@ext.uber.com | E19: ACCM | F19: US Spa Earner Acc/Pay | G19: agente | I19: 30 | J19: 30 | K19: 1_Stars_Percentage | L19: < | M19: 20 | N19: 20
A20: 45925.662 | B20: October | C20: Ospina, Michel | D20: mospin@ext.uber.com | E20: ACCM | F20: US Spa Earner Acc/Pay | G20: soporte | I20: 30 | J20: 30 | K20: KPI Octubre | L20: < | M20: 34 | N20: 34
A21: 45925.667 | B21: October | C21: Ospina, Michel | D21: mospin@ext.uber.com | E21: ACCM | F21: US Spa Earner Acc/Pay | G21: agente | I21: 30 | J21: 30 | K21: 1_Stars_Percentage | L21: < | M21: 20 | N21: 20
A22: 45925.669 | B22: October | C22: Ospina, Michel | D22: mospin@ext.uber.com | E22: ACCM | F22: LatAm U4B Triage | G22: agente | I22: 30 | J22: 30 | K22: 1_Stars_Percentage | L22: < | M22: 20 | N22: 20
A23: 45925.671 | B23: October | C23: Ospina, Michel | D23: mospin@ext.uber.com | E23: ACCM | F23: US Spa Earner Acc/Pay | G23: agente | I23: 30 | J23: 30 | K23: 1_Stars_Percentage | L23: < | M23: 20 | N23: 20
A24: 45925.679 | B24: October | C24: Ospina, Michel | D24: mospin@ext.uber.com | E24: ACCM | F24: US Spa Earner Acc/Pay | G24: agente | I24: 30 | J24: 30 | K24: 1_Stars_Percentage | L24: < | M24: 30 | N24: 30
... A28: 45926.388 | B28: October | C28: Ospina, Michel | D28: mospin@ext.uber.com | E28: ACCM | F28: US Spa Earner Acc/Pay | G28: agente | I28: 30 | J28: 30 | K28: 1_Stars_Percentage | L28: < | M28: 20 | N28: 20
A29: 45926.398 | B29: October | C29: Ospina, Michel | D29: mospin@ext.uber.com | E29: ACCM | G29: agente | I29: 30 | J29: 30 | K29: 1_Stars_Percentage | L29: < | M29: 20 | N29: 20
A30: 45926.445 | B30: October | C30: Ospina, Michel | D30: mospin@ext.uber.com | E30: ACCM | F30: US Spa Earner Acc/Pay | G30: agente | I30: 30 | J30: 30 | K30: 1_Stars_Percentage | L30: < | M30: 10 | N30: 10
A31: 45926.447 | B31: October | C31: Ospina, Michel | D31: mospin@ext.uber.com | E31: ACCM | F31: US Spa Earner Acc/Pay | G31: agente | I31: 30 | J31: 30 | K31: 1_Stars_Percentage | L31: < | M31: 10 | N31: 10
A32: 45926.478 | B32: October | C32: Ospina, Michel | D32: mospin@ext.uber.com | E32: ACCM | F32: US Spa Earner Acc/Pay | G32: agente | I32: 30 | J32: 30 | K32: 1_Stars_Percentage | L32: < | M32: 20 | N32: 20
A33: 45926.544 | B33: October | C33: Ospina, Michel | D33: mospin@ext.uber.com | E33: ACCM | F33: US Spa Earner Acc/Pay | G33: agente | I33: 30 | J33: 30 | K33: 1_Stars_Percentage | L33: < | M33: 20 | N33: 20
A34: 45926.571 | B34: October | C34: Ospina, Michel | D34: mospin@ext.uber.com | E34: ACCM | F34: US Spa Earner Acc/Pay | G34: agente | I34: 30 | J34: 30 | K34: 1_Stars_Percentage | L34: < | M34: 23 | N34: 23
A35: 45926.653 | B35: October | C35: Ospina, Michel | D35: mospin@ext.uber.com | E35: ACCM | F35: US Spa Earner Acc/Pay | G35: agente | I35: 30 | J35: 30 | K35: 1_Stars_Percentage | L35: < | M35: 10 | N35: 10
A36: 45926.653 | B36: October | C36: Ospina, Michel | D36: mospin@ext.uber.com | E36: ACCM | F36: US Spa Earner Acc/Pay | G36: agente | I36: 30 | J36: 30 | K36: Tickets_Solved_Volume | L36: < | M36: 10 | N36: 10
A37: 45926.665 | B37: October | C37: Ospina, Michel | D37: mospin@ext.uber.com | E37: ACCM | F37: Latam Eater Ring Fence | G37: agente | I37: 30 | J37: 30 | K37: 1_Stars_Percentage | L37: < | M37: 34 | N37: 34
A38: 45926.669 | B38: October | C38: Ospina, Michel | D38: mospin@ext.uber.com | E38: ACCM | F38: US Spa Earner Acc/Pay | G38: agente | I38: 30 | J38: 30 | K38: 1_Stars_Percentage | L38: < | M38: 34 | N38: 34
A39: 45926.67 | B39: October | C39: Ospina, Michel | D39: mospin@ext.uber.com | E39: ACCM | F39: Machine Learning | G39: agente | I39: 30 | J39: 30 | K39: 1_Stars_Percentage | L39: < | M39: 23 | N39: 23
A40: 45926.671 | B40: October | C40: Ospina, Michel | D40: mospin@ext.uber.com | E40: ACCM | F40: Machine Learning | G40: agente | I40: 30 | J40: 30 | K40: 1_Stars_Percentage | L40: < | M40: 23 | N40: 23
A41: 45926.675 | B41: October | C41: Ospina, Michel | D41: mospin@ext.uber.com | E41: ACCM | F41: US Spa Earner Acc/Pay | G41: agente | I41: 30 | J41: 30 | K41: 1_Stars_Percentage | L41: < | M41: 3 | N41: 3
... A54: 45929.524 | B54: October | C54: Ospina, Michel | D54: mospin@ext.uber.com | E54: ACCM | F54: US Spa Earner Acc/Pay | G54: agente | I54: 30 | J54: 30 | K54: Tickets_Solved_Volume | L54: < | M54: 10 | N54: 10

Sheet KPIS
A1: KPIS | C1: KPI | D1: SCORE
A2: 1_Stars_Percentage | C2: 1_Stars_Percentage | D2: SI
A3: Abandon_Percentage | C3: 1_Stars_Volume
A4: ABS | C4: Abandon_&_Skips_Percentage
A5: ABS Injus | C5: Abandon_Percentage | D5: SI
A6: ABS Jus | C6: Abandon_Volume
A7: AHT | C7: ABS | D7: SI
A8: ATRR | C8: ABS Injus | D8: SI
A9: CSAT | C9: ABS Jus | D9: SI
A10: FCR | C10: ADH
A11: Invalid_Transfers_Percentage | C11: AHT | D11: SI
A12: Quality@Uber | C12: Answered_Volume
A13: SHK TK | C13: ATRR | D13: SI
A14: Skips_Percentage | C14: Awaiting_Reply_Volume
A15: Tickets_Solved_Volume | C15: Callback_Outflow_Volume
A16: Total_Views_Volume | C16: Cherry_Picked_Percentage
A17: TPH | C17: Cherry_Picked_Volume
C18: Concurrency
C19: Converted_Chats_Percentage
C20: CPH
C21: CSAT | D21: SI
C22: Dial_Time_Mins
C23: DSAT
C24: FCR | D24: SI
C25: Hold_Mins
C26: HoldTime_Percentage
C27: Inbound_Call_Volume
C28: Invalid_Transfers_Percentage | D28: SI
C29: LAPH
C30: NPV_Percentage
C31: On_Queue_Elapsed_Time
C32: Open_Tickets_Volume
C33: PPH
C34: Quality@Uber | D34: SI
C35: REM_Percentage
C36: Reopen_Tickets_Percentage
C37: Shift_Completion_Percentage
C38: SHK TK | D38: SI
C39: ShortCalls_Volume
C40: Skips_Percentage | D40: SI
C41: SLA_Percentage
C42: Survey_Rate
C43: Talk_Time_Mins
C44: Tickets_Solved_Volume | D44: SI
C45: Total_Views_Volume | D45: SI
C46: TPH | D46: SI
C47: Transferred_Chats_Percetage
C48: Transfers_Volume
C49: WrapUp_Time_Mins
C50: WrapUp_Time_Percentage

Sheet Incentivos_12
A1: Fecha | B1: Nombre_incen | C1: LOB | D1: Fecha inicio | E1: fecha fin | F1: kpi | G1: condicion_general | H1: score_general | I1: valor_general | J1: operador (Piso 1) | K1: Key | L1: Score Key | M1: operador (Piso 2) | N1: score_2 (Piso 2) | O1: valor_(Piso 2) | P1: operador (Piso 3) | Q1: score (Piso 2) | R1: valor_piso_3 | S1: bms id | T1: Nombre
A2: 45901.439 | B2: 345 | C2: Latam U4B Phone Sales Churn12 | D2: 45665 | E2: 31/08/2025 | F2: 1_Stars_Percentage | G2: (≥) | H2: 7 | I2: 10000 | J2: (≥) | K2: Abandon_Percentage | L2: 10 | S2: 1270458 | T2: Ospina, Michel
A3: 45902.653 | B3: werwer | C3: Latam U4B Phone Sales Churn12 | D3: 45938 | E3: 31/08/2025 | F3: TPH | G3: (>) | H3: 6 | I3: 20000 | J3: (>) | K3: Tickets_Solved_Volume | L3: 400 | S3: 1270458 | T3: Ospina, Michel

Sheet H_C
A1: ccms id | B1: LOB | C1: CE | D1: Role | E1: Supervisor | F1: OAM | G1: OM | H1: Ext Account | I1: Region | J1: horas
A2: 728954 | B2: Latam Earner Conversion | C2: Londono, Isabel - 8954 | D2: Customer Expert | E2: Hernandez, Carlos | F2: Ayala, Jennifer | G2: Soler, Maria | H2: ilondo1@ext.uber.com | I2: Rebel LatAm
A3: 3773140 | B3: Latam Earner Conversion | C3: Hernande, Edith - 3140 | D3: Customer Expert | E3: Hernandez, Carlos | F3: Ayala, Jennifer | G3: Soler, Maria | H3: eherna48@ext.uber.com | I3: Rebel LatAm
A4: 752718 | B4: Earner Conversion Chat | C4: Hernandez, Carla - 2718 | D4: SME | E4: Munoz, Manuela | F4: Ayala, Jennifer | G4: Soler, Maria | H4: cherna85@ext.uber.com | I4: Rebel LatAm
A5: 4737226 | B5: Latam Earner Conversion | C5: Gonzalez, Erika - 7226 | D5: Customer Expert | E5: Hernandez, Carlos | F5: Ayala, Jennifer | G5: Soler, Maria | H5: egonza31@ext.uber.com | I5: Rebel LatAm
A6: 801763 | B6: Earner Conversion WhatsApp | C6: Ospina, Paula - 1763 | D6: Customer Expert | E6: Quintero, Yesica | F6: Galvis, Leslie | G6: Soler, Maria | H6: pospin1@ext.uber.com | I6: Rebel LatAm
A7: 5538879 | B7: Latam Earner Conversion | C7: Olmos, Kelly - 8879 | D7: Customer Expert | E7: Hernandez, Carlos | F7: Ayala, Jennifer | G7: Soler, Maria | H7: kolmos2@ext.uber.com | I7: Rebel LatAm
A8: 951124 | B8: Eats Menus Creation | C8: Moreno, Nancy - 1124 | D8: Customer Expert | E8: Caro, Lesly | F8: Martinez, Daniel | G8: Garcia, Helmer | H8: nmoren@ext.uber.com | I8: Rebel LatAm
A9: 4727234 | B9: Latam Earner Conversion | C9: Yepes, Jennifer - 7234 | D9: Customer Expert | E9: Hernandez, Carlos | F9: Ayala, Jennifer | G9: Soler, Maria | H9: jyepes6@ext.uber.com | I9: Rebel LatAm
A10: 1204240 | B10: US U4B Triage | C10: GarciaV, Jose - 4240 | D10: Customer Expert | E10: Galeano, Diana | F10: Ibarra, Maria | G10: Gonzalez, Cristian | H10: jgarci148@ext.uber.com | I10: Rebel US&C
A11: 4756641 | B11: Latam Earner Conversion | C11: Viveros, Johana - 6641 | D11: Customer Expert | E11: Hernandez, Carlos | F11: Ayala, Jennifer | G11: Soler, Maria | H11: jviver2@ext.uber.com | I11: Rebel LatAm
A12: 1289223 | B12: Restaurants Ads Sales | C12: GonzalezR, Fabian - 9223 | D12: Customer Expert | E12: Vasquez, Angel | F12: Ardila, Estiward | G12: Garcia, Helmer | H12: fgonza19@ext.uber.com | I12: Rebel LatAm
A13: 4968715 | B13: Latam Earner Conversion | C13: Orozco, Jaider - 8715 | D13: Customer Expert Cross Training | E13: Hernandez, Carlos | F13: Ayala, Jennifer | G13: Soler, Maria | H13: jorozc9@ext.uber.com | I13: Rebel LatAm
... A39: 4665286 | B39: Latam Phone Diamond | C39: Melo, Andres - 5286 | D39: SME | E39: Aguillon, Laura | F39: Aponte, Alejandra | G39: Garatejo, Natalia | H39: amelo22@ext.uber.com | I39: Rebel LatAm
A40: 2164860 | B40: US Cross Support | C40: Sanchez, Karen - 4860 | D40: Soporte | E40: Centeno, David | F40: Parra, Leonardo | G40: Ospina, Michel | H40: ksanch2@ext.uber.com | I40: Rebel US&C | J40: 42
A41: 5363195 | B41: Latam Phone Diamond | C41: Nieto, Ashly - 3195 | D41: Customer Expert | E41: Aguillon, Laura | F41: Aponte, Alejandra | G41: Garatejo, Natalia | H41: anieto6@ext.uber.com | I41: Rebel LatAm
A42: 2167116 | B42: U4B Phone Sales Churn | C42: GomezV, Diana - 7116 | D42: Customer Expert | E42: Beltran, Javier | F42: Mora, Daniel | G42: Gonzalez, Cristian | H42: dgomez22@ext.uber.com | I42: Rebel US&C
A43: 4721496 | B43: Latam Phone Diamond | C43: Montes, Ricardo - 1496 | D43: Customer Expert | E43: Aguillon, Laura | F43: Aponte, Alejandra | G43: Garatejo, Natalia | H43: rmonte30@ext.uber.com | I43: Rebel LatAm
A44: 2172302 | B44: Translations | C44: Villadiego, Joaquin - 2302 | D44: Customer Expert | E44: MorenoM, Maria | F44: Rodriguez, Camilo | G44: Garatejo, Natalia | H44: avilla64@ext.uber.com | I44: Rebel LatAm
A45: 4941896 | B45: Latam Phone Diamond | C45: Pardo, Dilan - 1896 | D45: Customer Expert | E45: Aguillon, Laura | F45: Aponte, Alejandra | G45: Garatejo, Natalia | H45: dpardo7@ext.uber.com | I45: Rebel LatAm
A46: 2185277 | B46: US U4B Triage | C46: Nino, Andres - 5277 | D46: Customer Expert | E46: Cabrejo, Jose | F46: Ibarra, Maria | G46: Gonzalez, Cristian | H46: anino@ext.uber.com | I46: Rebel US&C
A47: 5364019 | B47: Latam Phone Diamond | C47: Nova, Johan - 4019 | D47: Customer Expert | E47: Aguillon, Laura | F47: Aponte, Alejandra | G47: Garatejo, Natalia | H47: jnova3@ext.uber.com | I47: Rebel LatAm
A48: 2190483 | B48: LatAm SORT SPA | C48: Arce, Luz - 0483 | D48: Customer Expert | E48: Padilla, Sergio | F48: Amador, Brian | G48: Martinez, Wendy | H48: larce@ext.uber.com | I48: Rebel LatAm
A49: 5694881 | B49: Latam Phone Diamond | C49: Lozada, Edier - 4881 | D49: Customer Expert | E49: Aguillon, Laura | F49: Aponte, Alejandra | G49: Garatejo, Natalia | H49: elozad1@ext.uber.com | I49: Rebel LatAm
A50: 2201415 | B50: US Spa Consumer ACC | C50: Riascos, Miguel - 1415 | D50: Customer Expert Cross Training | E50: Centeno, David | F50: Parra, Leonardo | G50: Ospina, Michel | H50: mriasc1@ext.uber.com | I50: Rebel US&C | J50: 42 | L50: US Cross Support | M50: US Cross Support
A51: 5442779 | B51: Latam Phone Diamond | C51: Arango, Jhustin - 2779 | D51: Customer Expert | E51: Aguillon, Laura | F51: Aponte, Alejandra | G51: Garatejo, Natalia | H51: jarang21@ext.uber.com | I51: Rebel LatAm
A52: 2218922 | B52: Content Development POR | C52: Cuervo, Jose - 8922 | D52: Customer Expert | E52: Aguirre, Ruben | F52: Rodriguez, Camilo | G52: Garatejo, Natalia | H52: jcuerv1@ext.uber.com | I52: Rebel LatAm
A53: 5929864 | B53: Latam Phone Diamond | C53: Carrasco, Andres - 9864 | D53: Customer Expert | E53: Aguillon, Laura | F53: Aponte, Alejandra | G53: Garatejo, Natalia | H53: acarra16@ext.uber.com | I53: Rebel LatAm
A54: 2225563 | B54: Eats Menus EMEA Creation | C54: Santos, Yusunguaira - 5563 | D54: Customer Expert | E54: Triana, Juan | F54: Martinez, Daniel | G54: Garcia, Helmer | H54: fyusun1@ext.uber.com | I54: Rebel LatAm
A55: 5899595 | B55: Latam Phone Diamond | C55: Parra, Johan - 9595 | D55: Customer Expert | E55: Aguillon, Laura | F55: Aponte, Alejandra | G55: Garatejo, Natalia | H55: jparra37@ext.uber.com | I55: Rebel LatAm
A56: 2240540 | B56: Eats Menus Creation | C56: Hernandez, Daniela - 0540 | D56: Customer Expert | E56: Caro, Lesly | F56: Martinez, Daniel | G56: Garcia, Helmer | H56: sherna5@ext.uber.com | I56: Rebel LatAm
A57: 5976425 | B57: Latam Phone Diamond | C57: MartinezA, Juan - 6425 | D57: Customer Expert | E57: Aguillon, Laura | F57: Aponte, Alejandra | G57: Garatejo, Natalia | H57: jmarti277@ext.uber.com | I57: Rebel LatAm
A58: 2248847 | B58: IRT POR | C58: Cubillos, Jakeline - 8847 | D58: Customer Expert | E58: Soto, Marialbert | F58: Amador, Brian | G58: Martinez, Wendy | H58: jcubil1@ext.uber.com | I58: Rebel LatAm
A59: 5364315 | B59: Latam Phone Diamond | C59: Rodriguez, Angelica - 4315 | D59: Customer Expert | E59: Aguillon, Laura | F59: Aponte, Alejandra | G59: Garatejo, Natalia | H59: arodri223@ext.uber.com | I59: Rebel LatAm
A60: 2258969 | B60: US Spa Consumer ACC | C60: Riano, Sergio - 8969 | D60: Customer Expert | E60: Muskus, Claudia | F60: Parra, Leonardo | G60: Ospina, Michel | H60: sriano@ext.uber.com | I60: Rebel US&C | J60: 42 | L60: US Spa Consumer ACC | M60: Eats Phone US LO
A61: 5141712 | B61: Latam Phone Diamond | C61: Cortes, Julian - 1712 | D61: Customer Expert | E61: Aguillon, Laura | F61: Aponte, Alejandra | G61: Garatejo, Natalia | H61: jcorte42@ext.uber.com | I61: Rebel LatAm
A62: 2259318 | B62: US Phone Earner Spa | C62: Rosero, Cesar - 9318 | D62: Customer Expert | E62: Ortiz, Camilo | F62: Ospina, Michel | G62: Ospina, Michel | H62: croser@ext.uber.com | I62: Rebel US&C | J62: 42 | L62: US Spa Consumer ACC | M62: Eats Rest US Account
A63: 5533583 | B63: Latam Phone Diamond | C63: Tapia, Kevin - 3583 | D63: Customer Expert | E63: Aguillon, Laura | F63: Aponte, Alejandra | G63: Garatejo, Natalia | H63: ktapia1@ext.uber.com | I63: Rebel LatAm
A64: 2269452 | B64: Eats Phone US LO | C64: Arboleda, Juan - 9452 | D64: Customer Expert | E64: Madrid, Gabriela | F64: Mejia, Sebastian | G64: Soler, Maria | H64: jarbol3@ext.uber.com | I64: Rebel US&C | J64: {=UNIQUE(I64:I2629)} -> Rebel US&C
A65: 5898201 | B65: Latam Phone Diamond | C65: NinoZ, Maria - 8201 | D65: Customer Expert | E65: Aguillon, Laura | F65: Aponte, Alejandra | G65: Garatejo, Natalia | H65: mnino5@ext.uber.com | I65: Rebel LatAm | J65: Rebel LatAm
A66: 2269729 | B66: US Call To Ride | C66: Cortes, Joan - 9729 | D66: Customer Expert | E66: Soche, Juan | F66: Mora, Daniel | G66: Ospina, Michel | H66: jcorte7@ext.uber.com | I66: Rebel US&C
A67: 2275797 | B67: US Phone Earner Spa | C67: GonzalezG, Andrea - 5797 | D67: Customer Expert | E67: Mancipe, Laura | F67: Ospina, Michel | G67: Ospina, Michel | H67: agonza23@ext.uber.com | I67: Rebel US&C | J67: 42 | L67: US Phone Earner Spa | M67: US FNL SPA
A68: 3999849 | B68: Earner Conversion Chat | C68: Jimenez, Julian - 9849 | D68: Customer Expert | E68: Munoz, Manuela | F68: Ayala, Jennifer | G68: Soler, Maria | H68: jjimen67@ext.uber.com | I68: Rebel LatAm
A69: 2282732 | B69: ENG Growth | C69: Escobar, Yojana - 2732 | D69: Customer Expert | E69: Rey, Angel | F69: Ayala, Jennifer | G69: Soler, Maria | H69: yescob2@ext.uber.com | I69: Rebel LatAm
A70: 4012123 | B70: Earner Conversion Chat | C70: Moreno, Viviana - 2123 | D70: Customer Expert | E70: Munoz, Manuela | F70: Ayala, Jennifer | G70: Soler, Maria | H70: vmoren4@ext.uber.com | I70: Rebel LatAm
A71: 2292985 | B71: US Phone U4B | C71: Garcia, Eddward - 2985 | D71: Customer Expert | E71: Leon, Ximena | F71: Ibarra, Maria | G71: Gonzalez, Cristian | H71: egarci19@ext.uber.com | I71: Rebel US&C
A72: 4085665 | B72: Earner Conversion Chat | C72: Acevedo, Mayra - 5665 | D72: Customer Expert | E72: Munoz, Manuela | F72: Ayala, Jennifer | G72: Soler, Maria | H72: maceve9@ext.uber.com | I72: Rebel LatAm
A73: 2306026 | B73: Restaurants Ads Sales | C73: Vaquiro, Xiomara - 6026 | D73: Customer Expert | E73: Vasquez, Angel | F73: Ardila, Estiward | G73: Garcia, Helmer | H73: xvaqui@ext.uber.com | I73: Rebel LatAm
A74: 5538526 | B74: Earner Conversion Chat | C74: Nava, Ellyn - 8526 | D74: SME | E74: Munoz, Manuela | F74: Ayala, Jennifer | G74: Soler, Maria | H74: enava7@ext.uber.com | I74: Rebel LatAm
A75: 2307854 | B75: Brazil U4B Triage | C75: Betancur, Beatriz - 7854 | D75: Customer Expert | E75: Samaca, Bryan | F75: Ibarra, Maria | G75: Gonzalez, Cristian | H75: bbetan@ext.uber.com | I75: Rebel US&C
A76: 5051900 | B76: Earner Conversion Chat | C76: HerreraR, Jessica - 1900 | D76: Customer Expert | E76: Munoz, Manuela | F76: Ayala, Jennifer | G76: Soler, Maria | H76: jherre50@ext.uber.com | I76: Rebel LatAm
A77: 5361494 | B77: Earner Conversion Chat | C77: Aristizabal, Angie - 1494 | D77: Customer Expert Cross Training | E77: Munoz, Manuela | F77: Ayala, Jennifer | G77: Soler, Maria | H77: aarist5@ext.uber.com | I77: Rebel LatAm
A78: 2384414 | B78: Eats Phone Restaurants LatAm | C78: Espinosa, Leidy - 4414 | D78: Customer Expert | E78: Garzon, Nicoll | F78: Sabogal, Paula | G78: Celi, Juan | H78: lespin8@ext.uber.com | I78: Rebel LatAm
A79: 5828718 | B79: Earner Conversion Chat | C79: Gallego, Sebastian - 8718 | D79: Customer Expert | E79: Munoz, Manuela | F79: Ayala, Jennifer | G79: Soler, Maria | H79: sgalle12@ext.uber.com | I79: Rebel LatAm
... A94: 5926207 | B94: Earner Conversion Chat | C94: Mendoza, Johan - 6207 | D94: Customer Expert | E94: Munoz, Manuela | F94: Ayala, Jennifer | G94: Soler, Maria | H94: jmendo84@ext.uber.com | I94: Rebel LatAm
A95: 2644855 | B95: US Cross Support | C95: Gomez, Luisa - 4855 | D95: Customer Expert | E95: Centeno, David | F95: Ospina, Michel | G95: Ospina, Michel | H95: lgomez28@ext.uber.com | I95: Rebel US&C | J95: 42 | L95: US Phone Earner Spa | M95: US Chat Earner Spa
A96: 4386514 | B96: Earner Conversion Chat | C96: Correa, Julieth - 6514 | D96: Customer Expert | E96: Munoz, Manuela | F96: Ayala, Jennifer | G96: Soler, Maria | H96: jcorre37@ext.uber.com | I96: Rebel LatAm
A97: 2704721 | B97: US Chat Earner Spa | C97: Baron, Diana - 4721 | D97: Customer Expert | E97: Idarraga, Steven | F97: Arias, Fabio | G97: Ospina, Michel | H97: dbaron5@ext.uber.com | I97: Rebel US&C | J97: 42 | L97: US Cross Support
A98: 5743772 | B98: Earner Conversion Chat | C98: Moreno, Ana - 3772 | D98: Customer Expert | E98: Munoz, Manuela | F98: Ayala, Jennifer | G98: Soler, Maria | H98: amoren54@ext.uber.com | I98: Rebel LatAm
A99: 2768293 | B99: Content Development LatAm | C99: Henao, Maria - 8293 | D99: Customer Expert | E99: Aguirre, Ruben | F99: Rodriguez, Camilo | G99: Garatejo, Natalia | H99: mhenao1@ext.uber.com | I99: Rebel LatAm
A100: 5486538 | B100: Earner Conversion Chat | C100: Rios, Kelly - 6538 | D100: Customer Expert | E100: Munoz, Manuela | F100: Ayala, Jennifer | G100: Soler, Maria | H100: krios5@ext.uber.com | I100: Rebel LatAm
A101: 2816053 | B101: US Spa Earner Acc/Pay | C101: Castaneda, Maria - 6053 | D101: Customer Expert | E101: Benitez, Luis | F101: Parra, Leonardo | G101: Ospina, Michel | H101: mcasta17@ext.uber.com | I101: Rebel US&C | J101: 42 | L101: US Chat Earner Spa
A102: 4499084 | B102: Earner Conversion Chat | C102: Santamaria, Natalia - 9084 | D102: Customer Expert | E102: Munoz, Manuela | F102: Ayala, Jennifer | G102: Soler, Maria | H102: nsanta8@ext.uber.com | I102: Rebel LatAm
A103: 2912072 | B103: LatAm Phone IRT Sensitive | C103: Alvarado, Lizeth - 2072 | D103: Customer Expert | E103: Cuervo, Jhojan | F103: Jaramillo, Angie | G103: Martinez, Wendy | H103: lalvar8@ext.uber.com | I103: Rebel LatAm
A104: 4898296 | B104: LatAm IRT Theft Urgent | C104: Oliveros, Sergio - 8296 | D104: Customer Expert | E104: Ruiz, Josstin | F104: Murcia, Gustavo | G104: Martinez, Wendy | H104: solive37@ext.uber.com | I104: Rebel LatAm
A105: 2956647 | B105: Latam Sales New Verticals | C105: Trujillo, Nelson - 6647 | D105: Customer Expert | E105: Perez, Edwar | F105: Granados, Didier | G105: Garcia, Helmer | H105: ntruji2@ext.uber.com | I105: Rebel LatAm
A106: 5906006 | B106: LatAm IRT Theft Urgent | C106: Cortes, Leidy - 6006 | D106: Customer Expert | E106: Ruiz, Josstin | F106: Murcia, Gustavo | G106: Martinez, Wendy | H106: lcorte27@ext.uber.com | I106: Rebel LatAm
A107: 2987885 | B107: Mexico Receipt Support | C107: Espitia, Paula - 7885 | D107: Customer Expert | E107: Cano, Cristian | F107: Junco, Caren | G107: Ayala, Giselle | H107: pespit1@ext.uber.com | I107: Rebel LatAm
A108: 5847297 | B108: LatAm IRT Theft Urgent | C108: Perdomo, Juan - 7297 | D108: Customer Expert | E108: Ruiz, Josstin | F108: Murcia, Gustavo | G108: Martinez, Wendy | H108: jperdo5@ext.uber.com | I108: Rebel LatAm
A109: 3024170 | B109: LatAm SORT SPA | C109: Garcia, Mally - 4170 | D109: Customer Expert | E109: Padilla, Sergio | F109: Amador, Brian | G109: Martinez, Wendy | H109: mgarci178@ext.uber.com | I109: Rebel LatAm
A110: 5867460 | B110: LatAm IRT Theft Urgent | C110: Campos, Laura - 7460 | D110: Customer Expert | E110: Ruiz, Josstin | F110: Murcia, Gustavo | G110: Martinez, Wendy | H110: lcampo16@ext.uber.com | I110: Rebel LatAm
A111: 3046244 | B111: US Freight Carrier Inbound | C111: Fernandez, Javier - 6244 | D111: Customer Expert | E111: Rios, Andrea | F111: Guevara, Diego | G111: Soler, Maria | H111: jferna33@ext.uber.com | I111: Rebel US&C
A112: 3171770 | B112: LatAm IRT Theft Urgent | C112: Ledezma, Daniel - 1770 | D112: Customer Expert | E112: Ruiz, Josstin | F112: Murcia, Gustavo | G112: Martinez, Wendy | H112: dledez@ext.uber.com | I112: Rebel LatAm
A113: 3050288 | B113: Latam Consumer Off Trip EM | C113: Ferrucho, Alejandra - 0288 | D113: Customer Expert | E113: Cardona, Nicolle | F113: Suarez, Edwar | G113: Ayala, Giselle | H113: aferru@ext.uber.com | I113: Rebel LatAm
... A141: 5906075 | B141: LatAm IRT Theft Urgent | C141: Camargo, Jeinis - 6075 | D141: Customer Expert | E141: Ruiz, Josstin | F141: Murcia, Gustavo | G141: Martinez, Wendy | H141: jcamar31@ext.uber.com | I141: Rebel LatAm
A142: 3101825 | B142: US Spa Consumer ACC | C142: Lamus, Angelica - 1825 | D142: Customer Expert | E142: Muskus, Claudia | F142: Parra, Leonardo | G142: Ospina, Michel | H142: alamus@ext.uber.com | I142: Rebel US&C | J142: 42 | L142: US Spa Earner Acc/Pay
A143: 5439888 | B143: LatAm IRT Theft Urgent | C143: Valbuena, Daniel - 9888 | D143: Customer Expert | E143: Ruiz, Josstin | F143: Murcia, Gustavo | G143: Martinez, Wendy | H143: dvalbu2@ext.uber.com | I143: Rebel LatAm
A144: 3104166 | B144: Eats Menus EMEA Creation | C144: Aldana, Yurimy - 4166 | D144: Customer Expert | E144: Triana, Juan | F144: Martinez, Daniel | G144: Garcia, Helmer | H144: yaldan@ext.uber.com | I144: Rebel LatAm
A145: 3671369 | B145: Earner Conversion WhatsApp | C145: Molina, Carlos - 1369 | D145: Customer Expert | E145: Quintero, Yesica | F145: Galvis, Leslie | G145: Soler, Maria | H145: cmolin8@ext.uber.com | I145: Rebel LatAm
A146: 3112109 | B146: Latam U4B Email | C146: Soto, Yerson - 2109 | D146: Customer Expert | E146: Carreno, Jhon | F146: Ibarra, Maria | G146: Gonzalez, Cristian | H146: ysoto1@ext.uber.com | I146: Rebel US&C
A147: 3754441 | B147: Earner Conversion WhatsApp | C147: Rueda, Karen - 4441 | D147: Customer Expert | E147: Quintero, Yesica | F147: Galvis, Leslie | G147: Soler, Maria | H147: krueda1@ext.uber.com | I147: Rebel LatAm
A148: 3115262 | B148: Latam IRT L1L2 | C148: AcevedoM, Laura - 5262 | D148: Customer Expert | E148: Sepulveda, Heidy | F148: Murcia, Gustavo | G148: Martinez, Wendy | H148: laceve11@ext.uber.com | I148: Rebel LatAm
A149: 3866230 | B149: Earner Conversion WhatsApp | C149: Leal, Juan - 6230 | D149: SME | E149: Quintero, Yesica | F149: Galvis, Leslie | G149: Soler, Maria | H149: jleal5@ext.uber.com | I149: Rebel LatAm
A150: 3123300 | B150: US Phone Eng VS | C150: Matiz, Henry - 3300 | D150: Customer Expert | E150: Castaneda, Andres | F150: Ayala, Julian | G150: Ospina, Michel | H150: hmatiz@ext.uber.com | I150: Rebel US&C | J150: 42 | L150: US Spa Consumer ACC
A151: 4093815 | B151: Earner Conversion WhatsApp | C151: Henao, Laura - 3815 | D151: Customer Expert | E151: Quintero, Yesica | F151: Galvis, Leslie | G151: Soler, Maria | H151: lhenao5@ext.uber.com | I151: Rebel LatAm
A152: 3125870 | B152: LatAm IRT Theft Urgent | C152: Garcia, Ferney - 5870 | D152: Customer Expert | E152: Gutierrez, Sara | F152: Murcia, Gustavo | G152: Martinez, Wendy | H152: fgarci21@ext.uber.com | I152: Rebel LatAm
A153: 5197890 | B153: Earner Conversion WhatsApp | C153: Palacios, Jeimy - 7890 | D153: Customer Expert | E153: Quintero, Yesica | F153: Galvis, Leslie | G153: Soler, Maria | H153: jpalac33@ext.uber.com | I153: Rebel LatAm
A154: 3129228 | B154: US Call To Ride | C154: Bautista, Jaime - 9228 | D154: Customer Expert | E154: Soche, Juan | F154: Mora, Daniel | G154: Ospina, Michel | H154: jbauti16@ext.uber.com | I154: Rebel US&C
A155: 5102517 | B155: Earner Conversion WhatsApp | C155: Garces, Ana - 2517 | D155: Customer Expert Cross Training | E155: Quintero, Yesica | F155: Galvis, Leslie | G155: Soler, Maria | H155: agarce5@ext.uber.com | I155: Rebel LatAm
A156: 3139193 | B156: LatAm Phone IRT Sensitive | C156: Arguello, Leidy - 9193 | D156: Customer Expert | E156: Ovalle, Michel | F156: Jaramillo, Angie | G156: Martinez, Wendy | H156: largue1@ext.uber.com | I156: Rebel LatAm
A157: 5103634 | B157: Earner Conversion WhatsApp | C157: Bien, Jimmarie - 3634 | D157: Customer Expert | E157: Quintero, Yesica | F157: Galvis, Leslie | G157: Soler, Maria | H157: jbien1@ext.uber.com | I157: Rebel LatAm
A158: 3144705 | B158: LatAm Phone IRT Sensitive | C158: Llanos, Angela - 4705 | D158: Customer Expert | E158: Ovalle, Michel | F158: Jaramillo, Angie | G158: Martinez, Wendy | H158: allano2@ext.uber.com | I158: Rebel LatAm
A159: 4755132 | B159: Earner Conversion WhatsApp | C159: Alvarez, Daniela - 5132 | D159: Customer Expert | E159: Quintero, Yesica | F159: Galvis, Leslie | G159: Soler, Maria | H159: dalvar35@ext.uber.com | I159: Rebel LatAm
A160: 3144719 | B160: LatAm IRT Theft Urgent | C160: Gallardo, Lidia - 4719 | D160: Customer Expert | E160: Polo, Stephanie | F160: Murcia, Gustavo | G160: Martinez, Wendy | H160: lgalla2@ext.uber.com | I160: Rebel LatAm
A161: 5508880 | B161: Earner Conversion WhatsApp | C161: Espinal, Camilo - 8880 | D161: Customer Expert | E161: Quintero, Yesica | F161: Galvis, Leslie | G161: Soler, Maria | H161: cespin24@ext.uber.com | I161: Rebel LatAm
A162: 3144735 | B162: LatAm IIT | C162: Matamoros, Carlos - 4735 | D162: Customer Expert | E162: Rodriguez, Jaider | F162: Jaramillo, Angie | G162: Martinez, Wendy | H162: cmatam@ext.uber.com | I162: Rebel LatAm
... A165: 5611095 | B165: Earner Conversion WhatsApp | C165: Osuna, Dayana - 1095 | D165: Customer Expert | E165: Quintero, Yesica | F165: Galvis, Leslie | G165: Soler, Maria | H165: dosuna1@ext.uber.com | I165: Rebel LatAm
A166: 3150056 | B166: US Chat Earner Spa | C166: Mora, Francy - 0056 | D166: Customer Expert | E166: Idarraga, Steven | F166: Arias, Fabio | G166: Ospina, Michel | H166: fmora3@ext.uber.com | I166: Rebel US&C | J166: 42 | L166: US Phone Eng VS
A167: 5926036 | B167: Earner Conversion WhatsApp | C167: Cabrales, Javier - 6036 | D167: Customer Expert | E167: Quintero, Yesica | F167: Galvis, Leslie | G167: Soler, Maria | H167: jcabra6@ext.uber.com | I167: Rebel LatAm
A168: 3150082 | B168: US FNL SPA | C168: Tellez, Sandra - 0082 | D168: Customer Expert | E168: Muskus, Claudia | F168: Parra, Leonardo | G168: Ospina, Michel | H168: stelle1@ext.uber.com | I168: Rebel US&C | J168: 42 | L168: US Chat Earner Spa
...

Sheet Hoja 5
A1: ccms id | B1: LOB | C1: CE | D1: Role | E1: Supervisor | F1: OAM | G1: OM | H1: Ext Account
A2: 2116682 | B2: US Spa Earner Acc/Pay | C2: Pinzon, Cindy - 6682 | D2: Customer Expert | E2: Benitez, Luis | F2: Parra, Leonardo | G2: Ospina, Michel | H2: cpinzo1@ext.uber.com | J2: =VLOOKUP(A2,$R$2:$S$45,2,0) -> 94.445 | K2: $115.200,00 | L2: =VLOOKUP(A2,$U$3:$V$45,2,) -> 0 | R2: 3524085 | S2: 96.296667 | U2: CCMSID | V2: Score
A3: 2816053 | B3: US Spa Earner Acc/Pay | C3: Castaneda, Maria - 6053 | D3: Customer Expert | E3: Benitez, Luis | F3: Parra, Leonardo | G3: Ospina, Michel | H3: mcasta17@ext.uber.com | J3: =VLOOKUP(A3,$R$2:$S$45,2,0) -> 92.593333 | L3: =VLOOKUP(A3,$U$3:$V$45,2,) -> 14.102564 | R3: 5439948 | S3: 93.827778 | U3: 2116682 | V3: 0
A4: 3195695 | B4: US Spa Earner Acc/Pay | C4: MartinezS, Sebastian - 5695 | D4: Customer Expert | E4: Centeno, David | F4: Parra, Leonardo | G4: Ospina, Michel | H4: smarti23@ext.uber.com | J4: =VLOOKUP(A4,$R$2:$S$45,2,0) -> 90.124444 | L4: =VLOOKUP(A4,$U$3:$V$45,2,) -> 0 | R4: 5346664 | S4: 77.78 | U4: 2816053 | V4: 14.102564
A5: 3460648 | B5: US Spa Earner Acc/Pay | C5: Villada, Maria - 0648 | D5: Customer Expert Cross Training | E5: Centeno, David | F5: Parra, Leonardo | G5: Ospina, Michel | H5: mvilla153@ext.uber.com | J5: =VLOOKUP(A5,$R$2:$S$45,2,0) -> #N/A | L5: =VLOOKUP(A5,$U$3:$V$45,2,) -> 13.003096 | R5: 5321003 | S5: 90.123333 | U5: 3195695 | V5: 0
A6: 3524085 | B6: US Spa Earner Acc/Pay | C6: Gomez, Patricia - 4085 | D6: Customer Expert | E6: Muskus, Claudia | F6: Parra, Leonardo | G6: Ospina, Michel | H6: pgomez7@ext.uber.com | J6: =VLOOKUP(A6,$R$2:$S$45,2,0) -> 96.296667 | L6: =VLOOKUP(A6,$U$3:$V$45,2,) -> 9.8253275 | R6: 5437184 | S6: 91.6675 | U6: 3460648 | V6: 13.003096
A7: 3570218 | B7: US Spa Earner Acc/Pay | C7: Gomez, Erik - 0218 | D7: Customer Expert | E7: Benitez, Luis | F7: Parra, Leonardo | G7: Ospina, Michel | H7: edavid3@ext.uber.com | J7: =VLOOKUP(A7,$R$2:$S$45,2,0) -> 90.27875 | L7: =VLOOKUP(A7,$U$3:$V$45,2,) -> 11 | R7: 5327778 | S7: 81.481111 | U7: 3524085 | V7: 9.8253275
A8: 3924273 | B8: US Spa Earner Acc/Pay | C8: Espitia, Margy - 4273 | D8: Customer Expert | E8: Centeno, David | F8: Parra, Leonardo | G8: Ospina, Michel | H8: mespit5@ext.uber.com | J8: =VLOOKUP(A8,$R$2:$S$45,2,0) -> 80.248889 | L8: =VLOOKUP(A8,$U$3:$V$45,2,) -> 100 | R8: 5437211 | S8: 88.89 | U8: 3570218 | V8: 11
A9: 5346664 | B9: US Spa Earner Acc/Pay | C9: Orduna, Cesar - 6664 | D9: Customer Expert | E9: Benitez, Luis | F9: Parra, Leonardo | G9: Ospina, Michel | H9: cordun@ext.uber.com | J9: =VLOOKUP(A9,$R$2:$S$45,2,0) -> 77.78 | L9: =VLOOKUP(A9,$U$3:$V$45,2,) -> 22 | R9: 4747160 | S9: 76.543333 | U9: 3924273 | V9: 100
A10: 5349465 | B10: US Spa Earner Acc/Pay | C10: Diaz, Nicolas - 9465 | D10: Soporte | E10: Benitez, Luis | F10: Parra, Leonardo | G10: Ospina, Michel | H10: ndiaz17@ext.uber.com | J10: =VLOOKUP(A10,$R$2:$S$45,2,0) -> #N/A | L10: =VLOOKUP(A10,$U$3:$V$45,2,) -> 0 | R10: 5021467 | S10: 100 | U10: 5346664 | V10: 22
A11: 5438244 | B11: US Spa Earner Acc/Pay | C11: Pena, Marianggela - 8244 | D11: Customer Expert | E11: Benitez, Luis | F11: Parra, Leonardo | G11: Ospina, Michel | H11: mmunoz30@ext.uber.com | J11: =VLOOKUP(A11,$R$2:$S$45,2,0) -> 92.593333 | L11: =VLOOKUP(A11,$U$3:$V$45,2,) -> 5 | R11: 5333582 | S11: 90.27875 | U11: 5349465 | V11: 0
A12: 5528028 | B12: US Spa Earner Acc/Pay | C12: Torres, Carla - 8028 | D12: Customer Expert | E12: Benitez, Luis | F12: Parra, Leonardo | G12: Ospina, Michel | H12: ctorre65@ext.uber.com | J12: =VLOOKUP(A12,$R$2:$S$45,2,0) -> 86.1125 | L12: =VLOOKUP(A12,$U$3:$V$45,2,) -> 33 | R12: 3195695 | S12: 90.124444 | U12: 5438244 | V12: 5
A13: 5327778 | B13: US Spa Earner Acc/Pay | C13: Bogota, Yurian - 7778 | D13: Customer Expert | E13: Benitez, Luis | F13: Parra, Leonardo | G13: Ospina, Michel | H13: ybogot@ext.uber.com | J13: =VLOOKUP(A13,$R$2:$S$45,2,0) -> 81.481111 | L13: =VLOOKUP(A13,$U$3:$V$45,2,) -> 0 | R13: 5426155 | S13: 93.05625 | U13: 5528028 | V13: 33
A14: 5437184 | B14: US Spa Earner Acc/Pay | C14: Rincon, Estefania - 7184 | D14: Customer Expert | E14: Benitez, Luis | F14: Parra, Leonardo | G14: Ospina, Michel | H14: erinco4@ext.uber.com | J14: =VLOOKUP(A14,$R$2:$S$45,2,0) -> 91.6675 | L14: =VLOOKUP(A14,$U$3:$V$45,2,) -> 13.333333 | R14: 5327776 | S14: 94.445 | U14: 5327778 | V14: 0
... A44: 5134626 | B44: US Spa Earner Acc/Pay | C44: Portocarrero, Zuanny - 4626 | D44: Customer Expert | E44: Muskus, Claudia | F44: Parra, Leonardo | G44: Ospina, Michel | H44: zporto@ext.uber.com | J44: =VLOOKUP(A44,$R$2:$S$45,2,0) -> 96.296667 | L44: =VLOOKUP(A44,$U$3:$V$45,2,) -> 0 | R44: 3570218 | S44: 90.27875 | U44: 5072596 | V44: 0
R45: 5439875 | S45: 93.334 | U45: 5134626 | V45: 0

Sheet Registro_pisos
A1: Mes | B1: LOB | C1: ACCM | D1: Director | E1: H_c | F1: kEY | G1: Score_key_1 | H1: kEY_2 | I1: Score_key_2 | J1: kEY_3 | K1: Score_key_3 | L1: Bonus Structure | M1: KPI_1 | N1: Score_1 | O1: porcentage | P1: Participacion | Q1: KPI_1 | R1: Score_1 | S1: porcentage | T1: Participacion | U1: KPI_1 | V1: Score_1 | W1: porcentage | X1: Participacion | Y1: KPI_2 | Z1: Score_2 | AA1: porcentage | AB1: Participacion | AC1: KPI_2 | AD1: Score_2 | AE1: porcentage | AF1: Participacion | AG1: KPI_2 | AH1: Score_2 | AI1: porcentage | AJ1: Participacion | AK1: KPI_3 | AL1: Score_3 | AM1: porcentage | AN1: Participacion | AO1: KPI_3 | AP1: Score_3 | AQ1: porcentage | AR1: Participacion | AS1: KPI_3 | AT1: Score_3 | AU1: porcentage | AV1: Participacion | AW1: KPI_4 | AX1: Score_4 | AY1: porcentage | AZ1: Participacion | BA1: KPI_4 | BB1: Score_4 | BC1: porcentage | BD1: Participacion | BE1: KPI_4 | BF1: Score_4 | BG1: porcentage | BH1: Participacion | BI1: KPI_4 | BJ1: Score_4 | BK1: porcentage | BL1: Participacion | BM1: KPI_4 | BN1: Score_4 | BO1: porcentage | BP1: Participacion | BQ1: KPI_4 | BR1: Score_4 | BS1: porcentage | BT1: Participacion | BU1: KPI_4 | BV1: Score_4 | BW1: porcentage | BX1: Participacion | BY1: KPI_4 | BZ1: Score_4 | CA1: porcentage | CB1: Participacion | CC1: Additional Incentive | CD1: KPI_INC_1 | CE1: Score_iNC_1 | CF1: porcentage | CG1: Participacion | CH1: KPI_INC_2 | CI1: Score_iNC_2 | CJ1: porcentage | CK1: Participacion | CL1: KPI_INC_3 | CM1: Score_iNC_3 | CN1: porcentage | CO1: Participacion | CP1: KPI_INC_3 | CQ1: Score_iNC_3 | CR1: porcentage | CS1: Participacion | CT1: KPI_INC_3 | CU1: Score_iNC_3 | CV1: porcentage | CW1: Participacion | CX1: Decreased | CY1: KPI_DEC_1 | CZ1: Score_DEC_1 | DA1: porcentage | DB1: Participacion | DC1: KPI_DEC_2 | DD1: Score_DEC_2 | DE1: porcentage | DF1: Participacion | DG1: KPI_DEC_3 | DH1: Score_DEC_3 | DI1: porcentage | DJ1: Participacion | DK1: KPI_DEC_4 | DL1: Score_DEC_4 | DM1: porcentage | DN1: Participacion | DO1: KPI_DEC_4 | DP1: Score_DEC_4 | DQ1: porcentage | DR1: Participacion
A2: Enero | B2: US Spa Earner Acc/Pay | C2: Chamorro, Valentina | D2: Ospina, Michel | E2: =COUNTIFS(H_C!B:B, B2, H_C!D:D, "<>Soporte") -> 40 | H2: ABS Injus | I2: <=5% | M2: Quality@Uber | N2: >= 90% | O2: 30 | P2: 0.5 | Q2: Quality@Uber | R2: >= 92% | S2: 30 | T2: 80 | U2: Quality@Uber | V2: >= 95% | W2: 30 | X2: 100 | Y2: 1_Stars_Percentage | Z2: <=10 | AA2: 40 | AB2: 0.8 | AC2: 1_Stars_Percentage | AD2: <=7% | AE2: 40 | AF2: 0.9 | AG2: 1_Stars_Percentage | AH2: <=5% | AI2: 40 | AJ2: 100 | CD2: ABS | CE2: <10 | CF2: 20 | CY2: CSAT | CZ2: >=4 | DA2: 20

Sheet Metricas
A1: MES | B1: Semana | C1: Fecha | D1: Email | E1: CCMSID | F1: NombreAgente | G1: NombreSupervisor | H1: NombreACM | I1: SubLOB | J1: SubLOBSkill | K1: KPI | L1: CompI | M1: CompII | N1: KPICalc | R1: En la hoja Metricas, en la columma x dbee ser igual al de la hoja Incentivos en la columna F si es igual se hace el calculo teniendo en cuenta la fecha inicio y la fcha fin que estan en incentivos en las columnas D F en la G esta la condicion si es mayor menor o x en la H esta el score, y en la i esta el valor, en la y desde la j esta esto: operador (Piso 1) Key Score Key operador (Piso 2) score_2 (Piso 2) operador (Piso 2) operador (Piso 3) valor_1 (Piso 2) valor_piso_3, segun el piso se debe calular si es mayor o menor solo si lo tiene si no no se calcula
A2: 45665 | B2: 25/08/2025 | C2: 25/08/2025 | D2: narias5@ext.uber.com | E2: 5388863 | F2: 0 | G2: Luis Benitez Carvajal | H2: Leonardo Parra Orjuela | I2: US Spa Earner Acc/Pay | J2: US Spa Earner Acc/Pay | K2: Quality@Uber | L2: 100 | M2: 1 | N2: 100
A3: 28/08/2025 | B3: 18/08/2025 | C3: 28/08/2025 | D3: mospin@ext.uber.com | E3: 1270458 | F3: 0 | G3: Luis Benitez Carvajal | H3: Leonardo Parra Orjuela | I3: Latam U4B Phone Sales Churn12 | J3: Latam U4B Phone Sales Churn13 | K3: Csat | L3: 38 | M3: 0.84683333 | N3: 44.873056
A4: 28/08/2025 | B4: 45969 | C4: 28/08/2025 | D4: mospin@ext.uber.com | E4: 1270458 | F4: 0 | G4: Luis Benitez Carvajal | H4: Leonardo Parra Orjuela | I4: Latam U4B Phone Sales Churn12 | J4: Latam U4B Phone Sales Churn13 | K4: TPH | L4: 147 | M4: 5.876 | N4: 25.017018
A5: 28/08/2025 | B5: 18/08/2025 | C5: 28/08/2025 | D5: mospin@ext.uber.com | E5: 1270458 | F5: 0 | G5: Luis Benitez Carvajal | H5: Leonardo Parra Orjuela | I5: Latam U4B Phone Sales Churn12 | J5: Latam U4B Phone Sales Churn13 | K5: TPH | L5: 132 | M5: 5.6266667 | N5: 23.459716
A6: 28/08/2025 | B6: 18/08/2025 | C6: 28/08/2025 | D6: mospin@ext.uber.com | E6: 1270458 | F6: 0 | G6: Luis Benitez Carvajal | H6: Leonardo Parra Orjuela | I6: Latam U4B Phone Sales Churn12 | J6: Latam U4B Phone Sales Churn13 | L6: 127 | M6: 6.2503333 | N6: 20.318916
A7: 29/08/2025 | B7: 18/08/2025 | C7: 29/08/2025 | D7: mospin@ext.uber.com | E7: 1270458 | F7: 0 | G7: Luis Benitez Carvajal | H7: Leonardo Parra Orjuela | I7: Latam U4B Phone Sales Churn12 | J7: Latam U4B Phone Sales Churn13 | K7: TPH | L7: 122 | M7: 5.9885 | N7: 20.37238
A8: 45665 | B8: 28/07/2025 | C8: 45696 | D8: mospin@ext.uber.com | E8: 1270458 | F8: 0 | G8: David rafael Centeno padron | H8: Leonardo Parra Orjuela | I8: US Spa Earner Acc/Pay | J8: Latam U4B Phone Sales Churn13 | K8: Abandon_Percentage | L8: 0 | M8: 1 | N8: 0 | O8: 0
A9: 45665 | B9: 28/07/2025 | C9: 45696 | D9: mospin@ext.uber.com | E9: 1270458 | F9: 0 | G9: David rafael Centeno padron | H9: Leonardo Parra Orjuela | I9: US Spa Earner Acc/Pay | J9: Latam U4B Phone Sales Churn13 | K9: Skips_Percentage | L9: 0 | M9: 1 | N9: 0 | O9: 0
A10: 45665 | B10: 28/07/2025 | C10: 45696 | D10: mospin@ext.uber.com | E10: 1270458 | F10: 0 | G10: David rafael Centeno padron | H10: Leonardo Parra Orjuela | I10: US Spa Earner Acc/Pay | J10: Latam U4B Phone Sales Churn13 | K10: TPH | L10: 0 | M10: 0.009666667 | N10: 0 | O10: 0
A11: 45665 | B11: 28/07/2025 | C11: 45696 | D11: mospin@ext.uber.com | E11: 1270458 | F11: 0 | G11: David rafael Centeno padron | H11: Leonardo Parra Orjuela | I11: US Spa Earner Acc/Pay | J11: Latam U4B Phone Sales Churn13 | K11: Skips_Percentage | L11: 0 | M11: 7 | N11: 0 | O11: 0
A12: 45665 | B12: 28/07/2025 | C12: 45696 | D12: mospin@ext.uber.com | E12: 1270458 | F12: 0 | G12: David rafael Centeno padron | H12: Leonardo Parra Orjuela | I12: US Spa Earner Acc/Pay | J12: Latam U4B Phone Sales Churn13 | K12: Skips_Percentage | L12: 0 | M12: 108 | N12: 0 | O12: 0
A13: 45665 | B13: 28/07/2025 | C13: 45696 | D13: mospin@ext.uber.com | E13: 1270458 | F13: 0 | G13: David rafael Centeno padron | H13: Leonardo Parra Orjuela | I13: US Spa Earner Acc/Pay | J13: Latam U4B Phone Sales Churn13 | K13: Skips_Percentage | L13: 0 | M13: 2 | N13: 0 | O13: 0
A14: 45665 | B14: 28/07/2025 | C14: 45724 | D14: mospin@ext.uber.com | E14: 1270458 | F14: 0 | G14: David rafael Centeno padron | H14: Leonardo Parra Orjuela | I14: US Spa Earner Acc/Pay | J14: Latam U4B Phone Sales Churn13 | K14: Skips_Percentage | L14: 0 | M14: 1 | N14: 0 | O14: 0
A15: 45665 | B15: 28/07/2025 | C15: 45724 | D15: mospin@ext.uber.com | E15: 1270458 | F15: 0 | G15: David rafael Centeno padron | H15: Leonardo Parra Orjuela | I15: US Spa Earner Acc/Pay | J15: Latam U4B Phone Sales Churn13 | K15: Abandon_Percentage | L15: 0 | M15: 3 | N15: 0 | O15: 0
A16: 45665 | B16: 28/07/2025 | C16: 45724 | D16: mospin@ext.uber.com | E16: 1270458 | F16: 0 | G16: David rafael Centeno padron | H16: Leonardo Parra Orjuela | I16: US Spa Earner Acc/Pay | J16: Latam U4B Phone Sales Churn13 | K16: Skips_Percentage | L16: 0 | M16: 3 | N16: 0 | O16: 0
A17: 45665 | B17: 28/07/2025 | C17: 45724 | D17: mospin@ext.uber.com | E17: 1270458 | F17: 0 | G17: David rafael Centeno padron | H17: Leonardo Parra Orjuela | I17: US Spa Earner Acc/Pay | J17: Latam U4B Phone Sales Churn13 | K17: Total_Views_Volume | L17: 2 | N17: 2 | O17: #DIV/0!
A18: 45665 | B18: 28/07/2025 | C18: 45724 | D18: mospin@ext.uber.com | E18: 1270458 | F18: 0 | G18: David rafael Centeno padron | H18: Leonardo Parra Orjuela | I18: US Spa Earner Acc/Pay | J18: Latam U4B Phone Sales Churn13 | K18: ATRR | L18: 10500 | M18: 184 | N18: 57.065217 | O18: 57.065217
A19: 45665 | B19: 28/07/2025 | C19: 45724 | D19: mospin@ext.uber.com | E19: 1270458 | F19: 0 | G19: David rafael Centeno padron | H19: Leonardo Parra Orjuela | I19: US Spa Earner Acc/Pay | J19: Latam U4B Phone Sales Churn13 | K19: Skips_Percentage | L19: 0 | M19: 151 | N19: 0 | O19: 0
A20: 45665 | B20: 28/07/2025 | C20: 45724 | D20: mospin@ext.uber.com | E20: 1270458 | F20: 0 | G20: David rafael Centeno padron | H20: Leonardo Parra Orjuela | I20: US Spa Earner Acc/Pay | J20: Latam U4B Phone Sales Churn13 | K20: Total_Views_Volume | L20: 138 | N20: 138 | O20: #DIV/0!
A21: 45665 | B21: 28/07/2025 | C21: 45724 | D21: mospin@ext.uber.com | E21: 1270458 | F21: 0 | G21: David rafael Centeno padron | H21: Leonardo Parra Orjuela | I21: US Spa Earner Acc/Pay | J21: Latam U4B Phone Sales Churn13 | K21: TPH | L21: 97 | M21: 6.5173333 | N21: 14.883388 | O21: 14.883388
A22: 45665 | B22: 28/07/2025 | C22: 45724 | D22: mospin@ext.uber.com | E22: 1270458 | F22: 0 | G22: David rafael Centeno padron | H22: Leonardo Parra Orjuela | I22: US Spa Earner Acc/Pay | J22: Latam U4B Phone Sales Churn13 | K22: Abandon_Percentage | L22: 0 | M22: 3 | N22: 0 | O22: 0
A23: 45665 | B23: 28/07/2025 | C23: 45724 | D23: mospin@ext.uber.com | E23: 1270458 | F23: 0 | G23: David rafael Centeno padron | H23: Leonardo Parra Orjuela | I23: US Spa Earner Acc/Pay | J23: Latam U4B Phone Sales Churn13 | K23: Total_Views_Volume | L23: 3 | N23: 3 | O23: #DIV/0!
A24: 45665 | B24: 28/07/2025 | C24: 45724 | D24: mospin@ext.uber.com | E24: 1270458 | F24: 0 | G24: David rafael Centeno padron | H24: Leonardo Parra Orjuela | I24: US Spa Earner Acc/Pay | J24: Latam U4B Phone Sales Churn13 | K24: AHT | L24: 0.37 | M24: 0 | O24: #DIV/0!
A25: 45665 | B25: 28/07/2025 | C25: 45696 | D25: mospin@ext.uber.com | E25: 1270458 | F25: 0 | G25: David rafael Centeno padron | H25: Leonardo Parra Orjuela | I25: US Spa Earner Acc/Pay | J25: Latam U4B Phone Sales Churn13 | K25: AHT | L25: 0.58 | M25: 0 | O25: #DIV/0!
A26: 45665 | B26: 28/07/2025 | C26: 45696 | D26: mospin@ext.uber.com | E26: 1270458 | F26: 0 | G26: David rafael Centeno padron | H26: Leonardo Parra Orjuela | I26: US Spa Earner Acc/Pay | J26: Latam U4B Phone Sales Churn13 | K26: Tickets_Solved_Volume | L26: 1 | N26: 1 | O26: #DIV/0!
A27: 45665 | B27: 28/07/2025 | C27: 45696 | D27: mospin@ext.uber.com | E27: 1270458 | F27: 0 | G27: David rafael Centeno padron | H27: Leonardo Parra Orjuela | I27: US Spa Earner Acc/Pay | J27: Latam U4B Phone Sales Churn13 | K27: TPH | L27: 81 | M27: 5.0585 | N27: 16.012652 | O27: 16.012652
A28: 45665 | B28: 28/07/2025 | C28: 45696 | D28: mospin@ext.uber.com | E28: 1270458 | F28: 0 | G28: David rafael Centeno padron | H28: Leonardo Parra Orjuela | I28: US Spa Earner Acc/Pay | J28: Latam U4B Phone Sales Churn13 | K28: Abandon_Percentage | L28: 0 | M28: 1 | N28: 0 | O28: 0
A29: 45665 | B29: 28/07/2025 | C29: 45696 | D29: mospin@ext.uber.com | E29: 1270458 | F29: 0 | G29: David rafael Centeno padron | H29: Leonardo Parra Orjuela | I29: US Spa Earner Acc/Pay | J29: Latam U4B Phone Sales Churn13 | K29: Skips_Percentage | L29: 0 | M29: 1 | N29: 0 | O29: 0
A30: 45665 | B30: 28/07/2025 | C30: 45696 | D30: mospin@ext.uber.com | E30: 1270458 | F30: 0 | G30: David rafael Centeno padron | H30: Leonardo Parra Orjuela | I30: US Spa Earner Acc/Pay | J30: Latam U4B Phone Sales Churn13 | K30: Abandon_Percentage | L30: 0 | M30: 1 | N30: 0 | O30: 0
A31: 45665 | B31: 28/07/2025 | C31: 45696 | D31: mospin@ext.uber.com | E31: 1270458 | F31: 0 | G31: David rafael Centeno padron | H31: Leonardo Parra Orjuela | I31: US Spa Earner Acc/Pay | J31: Latam U4B Phone Sales Churn13 | K31: FCR | L31: 3500 | M31: 81 | N31: 43.209877 | O31: 43.209877
A32: 45665 | B32: 28/07/2025 | C32: 45696 | D32: mospin@ext.uber.com | E32: 1270458 | F32: 0 | G32: David rafael Centeno padron | H32: Leonardo Parra Orjuela | I32: US Spa Earner Acc/Pay | J32: Latam U4B Phone Sales Churn13 | K32: Skips_Percentage | L32: 0 | M32: 1 | N32: 0 | O32: 0
A33: 45665 | B33: 28/07/2025 | C33: 45696 | D33: mospin@ext.uber.com | E33: 1270458 | F33: 0 | G33: David rafael Centeno padron | H33: Leonardo Parra Orjuela | I33: US Spa Earner Acc/Pay | J33: Latam U4B Phone Sales Churn13 | K33: Abandon_Percentage | L33: 0 | M33: 1 | N33: 0 | O33: 0
A34: 45665 | B34: 28/07/2025 | C34: 45696 | D34: mospin@ext.uber.com | E34: 1270458 | F34: 0 | G34: David rafael Centeno padron | H34: Leonardo Parra Orjuela | I34: US Spa Earner Acc/Pay | J34: Latam U4B Phone Sales Churn13 | K34: Tickets_Solved_Volume | L34: 1 | N34: 1 | O34: #DIV/0!
A35: 45665 | B35: 28/07/2025 | C35: 45696 | D35: mospin@ext.uber.com | E35: 1270458 | F35: 0 | G35: David rafael Centeno padron | H35: Leonardo Parra Orjuela | I35: US Spa Earner Acc/Pay | J35: Latam U4B Phone Sales Churn13 | K35: TPH | L35: 1 | M35: 0 | O35: #DIV/0!
A36: 45665 | B36: 28/07/2025 | C36: 45696 | D36: mospin@ext.uber.com | E36: 1270458 | F36: 0 | G36: David rafael Centeno padron | H36: Leonardo Parra Orjuela | I36: US Spa Earner Acc/Pay | J36: Latam U4B Phone Sales Churn13 | K36: Total_Views_Volume | L36: 1 | N36: 1 | O36: #DIV/0!
A37: 45665 | B37: 28/07/2025 | C37: 45696 | D37: mospin@ext.uber.com | E37: 1270458 | F37: 0 | G37: David rafael Centeno padron | H37: Leonardo Parra Orjuela | I37: US Spa Earner Acc/Pay | J37: Latam U4B Phone Sales Churn13 | K37: AHT | L37: 303.51 | M37: 81 | N37: 3.747037 | O37: 3.747037
A38: 45665 | B38: 28/07/2025 | C38: 45696 | D38: mospin@ext.uber.com | E38: 1270458 | F38: 0 | G38: David rafael Centeno padron | H38: Leonardo Parra Orjuela | I38: US Spa Earner Acc/Pay | J38: Latam U4B Phone Sales Churn13 | K38: Skips_Percentage | L38: 0 | M38: 3 | N38: 0 | O38: 0
A39: 45665 | B39: 28/07/2025 | C39: 45696 | D39: mospin@ext.uber.com | E39: 1270458 | F39: 0 | G39: David rafael Centeno padron | H39: Leonardo Parra Orjuela | I39: US Spa Earner Acc/Pay | J39: Latam U4B Phone Sales Churn13 | K39: Abandon_Percentage | L39: 0 | M39: 2 | N39: 0 | O39: 0
A40: 45665 | B40: 28/07/2025 | C40: 45696 | D40: mospin@ext.uber.com | E40: 1270458 | F40: 0 | G40: David rafael Centeno padron | H40: Leonardo Parra Orjuela | I40: US Spa Earner Acc/Pay | J40: Latam U4B Phone Sales Churn13 | K40: Total_Views_Volume | L40: 7 | N40: 7 | O40: #DIV/0!
A41: 45665 | B41: 28/07/2025 | C41: 45696 | D41: mospin@ext.uber.com | E41: 1270458 | F41: 0 | G41: David rafael Centeno padron | H41: Leonardo Parra Orjuela | I41: Latam U4B Phone Sales Churn13 | J41: Latam U4B Phone Sales Churn13 | K41: 1_Stars_Percentage | L41: 300 | M41: 16 | N41: 18.75 | O41: 18.75
A42: 45665 | B42: 28/07/2025 | C42: 45696 | D42: mospin@ext.uber.com | E42: 1270458 | F42: 0 | G42: David rafael Centeno padron | H42: Leonardo Parra Orjuela | I42: US Spa Earner Acc/Pay | J42: Latam U4B Phone Sales Churn13 | K42: Abandon_Percentage | L42: 900 | M42: 108 | N42: 8.3333333 | O42: 8.3333333
A43: 45665 | B43: 28/07/2025 | C43: 45696 | D43: mospin@ext.uber.com | E43: 1270458 | F43: 0 | G43: David rafael Centeno padron | H43: Leonardo Parra Orjuela | I43: US Spa Earner Acc/Pay | J43: Latam U4B Phone Sales Churn13 | K43: CSAT | L43: 58 | M43: 16 | N43: 3.625 | O43: 3.625
A44: 45665 | B44: 28/07/2025 | C44: 45696 | D44: mospin@ext.uber.com | E44: 1270458 | F44: 0 | G44: David rafael Centeno padron | H44: Leonardo Parra Orjuela | I44: US Spa Earner Acc/Pay | J44: Latam U4B Phone Sales Churn13 | K44: TPH | L44: 0 | M44: 0.011333333 | N44: 0 | O44: 0
A45: 45665 | B45: 28/07/2025 | C45: 45696 | D45: mospin@ext.uber.com | E45: 1270458 | F45: 0 | G45: David rafael Centeno padron | H45: Leonardo Parra Orjuela | I45: US Spa Earner Acc/Pay | J45: Latam U4B Phone Sales Churn13 | K45: AHT | L45: 0 | M45: 1 | N45: 0 | O45: 0
A46: 45665 | B46: 28/07/2025 | C46: 45696 | D46: mospin@ext.uber.com | E46: 1270458 | F46: 0 | G46: David rafael Centeno padron | H46: Leonardo Parra Orjuela | I46: US Spa Earner Acc/Pay | J46: Latam U4B Phone Sales Churn13 | K46: Total_Views_Volume | L46: 2 | N46: 2 | O46: #DIV/0!
A47: 45665 | B47: 28/07/2025 | C47: 45696 | D47: mospin@ext.uber.com | E47: 1270458 | F47: 0 | G47: David rafael Centeno padron | H47: Leonardo Parra Orjuela | I47: US Spa Earner Acc/Pay | J47: Latam U4B Phone Sales Churn13 | K47: Skips_Percentage | L47: 0 | M47: 1 | N47: 0 | O47: 0
A48: 45665 | B48: 28/07/2025 | C48: 45696 | D48: mospin@ext.uber.com | E48: 1270458 | F48: 0 | G48: David rafael Centeno padron | H48: Leonardo Parra Orjuela | I48: US Spa Earner Acc/Pay | J48: Latam U4B Phone Sales Churn13 | K48: Total_Views_Volume | L48: 1 | N48: 1 | O48: #DIV/0!
A49: 45665 | B49: 28/07/2025 | C49: 45696 | D49: mospin@ext.uber.com | E49: 1270458 | F49: 0 | G49: David rafael Centeno padron | H49: Leonardo Parra Orjuela | I49: US Spa Earner Acc/Pay | J49: Latam U4B Phone Sales Churn13 | K49: ABS Injus | L49: 0 | M49: 8.5 | N49: 0 | O49: 0
A50: 45665 | B50: 28/07/2025 | C50: 45696 | D50: mospin@ext.uber.com | E50: 1270458 | F50: 0 | G50: David rafael Centeno padron | H50: Leonardo Parra Orjuela | I50: US Spa Earner Acc/Pay | J50: Latam U4B Phone Sales Churn13 | K50: Tickets_Solved_Volume | L50: 81 | N50: 81 | O50: #DIV/0!
A51: 45665 | B51: 28/07/2025 | C51: 45696 | D51: mospin@ext.uber.com | E51: 1270458 | F51: 0 | G51: David rafael Centeno padron | H51: Leonardo Parra Orjuela | I51: US Spa Earner Acc/Pay | J51: Latam U4B Phone Sales Churn13 | K51: Abandon_Percentage | L51: 0 | M51: 3 | N51: 0 | O51: 0
A52: 45665 | B52: 28/07/2025 | C52: 45696 | D52: mospin@ext.uber.com | E52: 1270458 | F52: 0 | G52: David rafael Centeno padron | H52: Leonardo Parra Orjuela | I52: US Spa Earner Acc/Pay | J52: Latam U4B Phone Sales Churn13 | K52: Total_Views_Volume | L52: 3 | N52: 3 | O52: #DIV/0!
A53: 45665 | B53: 28/07/2025 | C53: 45696 | D53: mospin@ext.uber.com | E53: 1270458 | F53: 0 | G53: David rafael Centeno padron | H53: Leonardo Parra Orjuela | I53: US Spa Earner Acc/Pay | J53: Latam U4B Phone Sales Churn13 | K53: FCR | L53: 0 | M53: 1 | N53: 0 | O53: 0
A54: 45665 | B54: 28/07/2025 | C54: 45696 | D54: mospin@ext.uber.com | E54: 1270458 | F54: 0 | G54: David rafael Centeno padron | H54: Leonardo Parra Orjuela | I54: US Spa Earner Acc/Pay | J54: Latam U4B Phone Sales Churn13 | K54: AHT | L54: 8.25 | M54: 1 | N54: 8.25 | O54: 8.25
A55: 45665 | B55: 28/07/2025 | C55: 45696 | D55: mospin@ext.uber.com | E55: 1270458 | F55: 0 | G55: David rafael Centeno padron | H55: Leonardo Parra Orjuela | I55: US Spa Earner Acc/Pay | J55: Latam U4B Phone Sales Churn13 | K55: FCR | L55: 0 | M55: 1 | N55: 0 | O55: 0
A56: 45665 | B56: 28/07/2025 | C56: 45696 | D56: mospin@ext.uber.com | E56: 1270458 | F56: 0 | G56: David rafael Centeno padron | H56: Leonardo Parra Orjuela | I56: US Spa Earner Acc/Pay | J56: Latam U4B Phone Sales Churn13 | K56: TPH | L56: 1 | M56: 0.1375 | N56: 7.2727273 | O56: 7.2727273
A57: 45665 | B57: 28/07/2025 | C57: 45696 | D57: mospin@ext.uber.com | E57: 1270458 | F57: 0 | G57: David rafael Centeno padron | H57: Leonardo Parra Orjuela | I57: US Spa Earner Acc/Pay | J57: Latam U4B Phone Sales Churn13 | K57: ATRR | L57: 9400 | M57: 168 | N57: 55.952381 | O57: 55.952381
A58: 45665 | B58: 28/07/2025 | C58: 45696 | D58: mospin@ext.uber.com | E58: 1270458 | F58: 0 | G58: David rafael Centeno padron | H58: Leonardo Parra Orjuela | I58: US Spa Earner Acc/Pay | J58: Latam U4B Phone Sales Churn13 | K58: Total_Views_Volume | L58: 1 | N58: 1 | O58: #DIV/0!
A59: 45665 | B59: 28/07/2025 | C59: 45724 | D59: mospin@ext.uber.com | E59: 1270458 | F59: 0 | G59: David rafael Centeno padron | H59: Leonardo Parra Orjuela | I59: Latam U4B Phone Sales Churn13 | J59: Latam U4B Phone Sales Churn13 | K59: 1_Stars_Percentage | L59: 100 | M59: 16 | N59: 6.25 | O59: 6.25
A60: 45665 | B60: 28/07/2025 | C60: 45724 | D60: mospin@ext.uber.com | E60: 1270458 | F60: 0 | G60: David rafael Centeno padron | H60: Leonardo Parra Orjuela | I60: US Spa Earner Acc/Pay | J60: Latam U4B Phone Sales Churn13 | K60: Skips_Percentage | L60: 0 | M60: 2 | N60: 0 | O60: 0
A61: 45665 | B61: 28/07/2025 | C61: 45724 | D61: mospin@ext.uber.com | E61: 1270458 | F61: 0 | G61: David rafael Centeno padron | H61: Leonardo Parra Orjuela | I61: US Spa Earner Acc/Pay | J61: Latam U4B Phone Sales Churn13 | K61: Total_Views_Volume | L61: 2 | N61: 2 | O61: #DIV/0!
A62: 45665 | B62: 28/07/2025 | C62: 45724 | D62: mospin@ext.uber.com | E62: 1270458 | F62: 0 | G62: David rafael Centeno padron | H62: Leonardo Parra Orjuela | I62: US Spa Earner Acc/Pay | J62: Latam U4B Phone Sales Churn13 | K62: Abandon_Percentage | L62: 0 | M62: 1 | N62: 0 | O62: 0
A63: 45665 | B63: 28/07/2025 | C63: 45724 | D63: mospin@ext.uber.com | E63: 1270458 | F63: 0 | G63: David rafael Centeno padron | H63: Leonardo Parra Orjuela | I63: US Spa Earner Acc/Pay | J63: Latam U4B Phone Sales Churn13 | K63: Total_Views_Volume | L63: 1 | N63: 1 | O63: #DIV/0!
A64: 45665 | B64: 28/07/2025 | C64: 45724 | D64: mospin@ext.uber.com | E64: 1270458 | F64: 0 | G64: David rafael Centeno padron | H64: Leonardo Parra Orjuela | I64: US Spa Earner Acc/Pay | J64: Latam U4B Phone Sales Churn13 | K64: TPH | L64: 0 | M64: 0.006166667 | N64: 0 | O64: 0
A65: 45665 | B65: 28/07/2025 | C65: 45724 | D65: mospin@ext.uber.com | E65: 1270458 | F65: 0 | G65: David rafael Centeno padron | H65: Leonardo Parra Orjuela | I65: US Spa Earner Acc/Pay | J65: Latam U4B Phone Sales Churn13 | K65: Abandon_Percentage | L65: 0 | M65: 2 | N65: 0 | O65: 0
A66: 45665 | B66: 28/07/2025 | C66: 45724 | D66: mospin@ext.uber.com | E66: 1270458 | F66: 0 | G66: David rafael Centeno padron | H66: Leonardo Parra Orjuela | I66: US Spa Earner Acc/Pay | J66: Latam U4B Phone Sales Churn13 | K66: Abandon_Percentage | L66: 0 | M66: 1 | N66: 0 | O66: 0
A67: 45665 | B67: 28/07/2025 | C67: 45724 | D67: mospin@ext.uber.com | E67: 1270458 | F67: 0 | G67: David rafael Centeno padron | H67: Leonardo Parra Orjuela | I67: US Spa Earner Acc/Pay | J67: Latam U4B Phone Sales Churn13 | K67: Abandon_Percentage | L67: 1300 | M67: 151 | N67: 8.6092715 | O67: 8.6092715
A68: 45665 | B68: 28/07/2025 | C68: 45724 | D68: mospin@ext.uber.com | E68: 1270458 | F68: 0 | G68: David rafael Centeno padron | H68: Leonardo Parra Orjuela | I68: US Spa Earner Acc/Pay | J68: Latam U4B Phone Sales Churn13 | K68: CSAT | L68: 61 | M68: 16 | N68: 3.8125 | O68: 3.8125
A69: 45665 | B69: 28/07/2025 | C69: 45724 | D69: mospin@ext.uber.com | E69: 1270458 | F69: 0 | G69: David rafael Centeno padron | H69: Leonardo Parra Orjuela | I69: US Spa Earner Acc/Pay | J69: Latam U4B Phone Sales Churn13 | K69: Skips_Percentage | L69: 0 | M69: 1 | N69: 0 | O69: 0
A70: 45665 | B70: 28/07/2025 | C70: 45724 | D70: mospin@ext.uber.com | E70: 1270458 | F70: 0 | G70: David rafael Centeno padron | H70: Leonardo Parra Orjuela | I70: US Spa Earner Acc/Pay | J70: Latam U4B Phone Sales Churn13 | K70: Total_Views_Volume | L70: 8 | N70: 8 | O70: #DIV/0!
A71: 45665 | B71: 28/07/2025 | C71: 45724 | D71: mospin@ext.uber.com | E71: 1270458 | F71: 0 | G71: David rafael Centeno padron | H71: Leonardo Parra Orjuela | I71: US Spa Earner Acc/Pay | J71: Latam U4B Phone Sales Churn13 | K71: Abandon_Percentage | L71: 0 | M71: 2 | N71: 0 | O71: 0
A72: 45665 | B72: 28/07/2025 | C72: 45724 | D72: mospin@ext.uber.com | E72: 1270458 | F72: 0 | G72: David rafael Centeno padron | H72: Leonardo Parra Orjuela | I72: US Spa Earner Acc/Pay | J72: Latam U4B Phone Sales Churn13 | K72: Total_Views_Volume | L72: 1 | N72: 1 | O72: #DIV/0!
A73: 45665 | B73: 28/07/2025 | C73: 45724 | D73: mospin@ext.uber.com | E73: 1270458 | F73: 0 | G73: David rafael Centeno padron | H73: Leonardo Parra Orjuela | I73: US Spa Earner Acc/Pay | J73: Latam U4B Phone Sales Churn13 | K73: Total_Views_Volume | L73: 1 | N73: 1 | O73: #DIV/0!
A74: 45665 | B74: 45755 | C74: 45755 | D74: mospin@ext.uber.com | E74: 1270458 | F74: 0 | G74: David rafael Centeno padron | H74: Leonardo Parra Orjuela | I74: US Spa Earner Acc/Pay | J74: Latam U4B Phone Sales Churn13 | K74: Skips_Percentage | L74: 0 | M74: 1 | N74: 0 | O74: 0
A75: 45665 | B75: 45755 | C75: 45755 | D75: mospin@ext.uber.com | E75: 1270458 | F75: 0 | G75: David rafael Centeno padron | H75: Leonardo Parra Orjuela | I75: US Spa Earner Acc/Pay | J75: Latam U4B Phone Sales Churn13 | K75: Invalid_Transfers_Percentage | L75: 0 | M75: 35 | N75: 0 | O75: 0
A76: 45665 | B76: 45755 | C76: 45755 | D76: mospin@ext.uber.com | E76: 1270458 | F76: 0 | G76: David rafael Centeno padron | H76: Leonardo Parra Orjuela | I76: US Spa Earner Acc/Pay | J76: Latam U4B Phone Sales Churn13 | K76: TPH | L76: 0 | M76: 0.010666667 | N76: 0 | O76: 0
A77: 45665 | B77: 45755 | C77: 45755 | D77: mospin@ext.uber.com | E77: 1270458 | F77: 0 | G77: David rafael Centeno padron | H77: Leonardo Parra Orjuela | I77: US Spa Earner Acc/Pay | J77: Latam U4B Phone Sales Churn13 | K77: Skips_Percentage | L77: 0 | M77: 2 | N77: 0 | O77: 0
A78: 45665 | B78: 45755 | C78: 45755 | D78: mospin@ext.uber.com | E78: 1270458 | F78: 0 | G78: David rafael Centeno padron | H78: Leonardo Parra Orjuela | I78: US Spa Earner Acc/Pay | J78: Latam U4B Phone Sales Churn13 | K78: Invalid_Transfers_Percentage | L78: 2400 | M78: 32 | N78: 75 | O78: 75
A79: 45665 | B79: 45755 | C79: 45755 | D79: mospin@ext.uber.com | E79: 1270458 | F79: 0 | G79: David rafael Centeno padron | H79: Leonardo Parra Orjuela | I79: US Spa Earner Acc/Pay | J79: Latam U4B Phone Sales Churn13 | K79: Abandon_Percentage | L79: 0 | M79: 3 | N79: 0 | O79: 0
A80: 45665 | B80: 45755 | C80: 45755 | D80: mospin@ext.uber.com | E80: 1270458 | F80: 0 | G80: David rafael Centeno padron | H80: Leonardo Parra Orjuela | I80: US Spa Earner Acc/Pay | J80: Latam U4B Phone Sales Churn13 | K80: Total_Views_Volume | L80: 3 | N80: 3 | O80: #DIV/0!
A81: 45665 | B81: 45755 | C81: 45755 | D81: mospin@ext.uber.com | E81: 1270458 | F81: 0 | G81: David rafael Centeno padron | H81: Leonardo Parra Orjuela | I81: US Spa Earner Acc/Pay | J81: Latam U4B Phone Sales Churn13 | K81: Invalid_Transfers_Percentage | L81: 300 | M81: 32 | N81: 9.375 | O81: 9.375
A82: 45665 | B82: 45755 | C82: 45755 | D82: mospin@ext.uber.com | E82: 1270458 | F82: 0 | G82: David rafael Centeno padron | H82: Leonardo Parra Orjuela | I82: US Spa Earner Acc/Pay | J82: Latam U4B Phone Sales Churn13 | K82: Abandon_Percentage | L82: 0 | M82: 1 | N82: 0 | O82: 0
A83: 45665 | B83: 45755 | C83: 45755 | D83: mospin@ext.uber.com | E83: 1270458 | F83: 0 | G83: David rafael Centeno padron | H83: Leonardo Parra Orjuela | I83: US Spa Earner Acc/Pay | J83: Latam U4B Phone Sales Churn13 | K83: Total_Views_Volume | L83: 1 | N83: 1 | O83: #DIV/0!
A84: 45665 | B84: 45755 | C84: 45755 | D84: mospin@ext.uber.com | E84: 1270458 | F84: 0 | G84: David rafael Centeno padron | H84: Leonardo Parra Orjuela | I84: US Spa Earner Acc/Pay | J84: Latam U4B Phone Sales Churn13 | K84: Invalid_Transfers_Percentage | L84: 4700 | M84: 102 | N84: 46.078431 | O84: 46.078431
A85: 45665 | B85: 28/07/2025 | C85: 45724 | D85: mospin@ext.uber.com | E85: 1270458 | F85: 0 | G85: David rafael Centeno padron | H85: Leonardo Parra Orjuela | I85: US Spa Earner Acc/Pay | J85: Latam U4B Phone Sales Churn13 | K85: Total_Views_Volume | L85: 1 | N85: 1 | O85: #DIV/0!
A86: 45665 | B86: 28/07/2025 | C86: 45724 | D86: mospin@ext.uber.com | E86: 1270458 | F86: 0 | G86: David rafael Centeno padron | H86: Leonardo Parra Orjuela | I86: US Spa Earner Acc/Pay | J86: Latam U4B Phone Sales Churn13 | K86: Abandon_Percentage | L86: 0 | M86: 8 | N86: 0 | O86: 0
A87: 45665 | B87: 28/07/2025 | C87: 45724 | D87: mospin@ext.uber.com | E87: 1270458 | F87: 0 | G87: David rafael Centeno padron | H87: Leonardo Parra Orjuela | I87: US Spa Earner Acc/Pay | J87: Latam U4B Phone Sales Churn13 | K87: AHT | L87: 0.58 | M87: 0 | O87: #DIV/0!
A88: 45665 | B88: 28/07/2025 | C88: 45724 | D88: mospin@ext.uber.com | E88: 1270458 | F88: 0 | G88: David rafael Centeno padron | H88: Leonardo Parra Orjuela | I88: US Spa Earner Acc/Pay | J88: Latam U4B Phone Sales Churn13 | K88: Skips_Percentage | L88: 0 | M88: 2 | N88: 0 | O88: 0
A89: 45665 | B89: 28/07/2025 | C89: 45724 | D89: mospin@ext.uber.com | E89: 1270458 | F89: 0 | G89: David rafael Centeno padron | H89: Leonardo Parra Orjuela | I89: US Spa Earner Acc/Pay | J89: Latam U4B Phone Sales Churn13 | K89: ABS Injus | L89: 0 | M89: 7 | N89: 0 | O89: 0
A90: 45665 | B90: 28/07/2025 | C90: 45724 | D90: mospin@ext.uber.com | E90: 1270458 | F90: 0 | G90: David rafael Centeno padron | H90: Leonardo Parra Orjuela | I90: US Spa Earner Acc/Pay | J90: Latam U4B Phone Sales Churn13 | K90: Tickets_Solved_Volume | L90: 97 | N90: 97 | O90: #DIV/0!
A91: 45665 | B91: 28/07/2025 | C91: 45724 | D91: mospin@ext.uber.com | E91: 1270458 | F91: 0 | G91: David rafael Centeno padron | H91: Leonardo Parra Orjuela | I91: US Spa Earner Acc/Pay | J91: Latam U4B Phone Sales Churn13 | K91: Skips_Percentage | L91: 0 | M91: 1 | N91: 0 | O91: 0
A92: 45665 | B92: 28/07/2025 | C92: 45724 | D92: mospin@ext.uber.com | E92: 1270458 | F92: 0 | G92: David rafael Centeno padron | H92: Leonardo Parra Orjuela | I92: US Spa Earner Acc/Pay | J92: Latam U4B Phone Sales Churn13 | K92: Total_Views_Volume | L92: 2 | N92: 2 | O92: #DIV/0!
A93: 45665 | B93: 28/07/2025 | C93: 45724 | D93: mospin@ext.uber.com | E93: 1270458 | F93: 0 | G93: David rafael Centeno padron | H93: Leonardo Parra Orjuela | I93: US Spa Earner Acc/Pay | J93: Latam U4B Phone Sales Churn13 | K93: Skips_Percentage | L93: 0 | M93: 1 | N93: 0 | O93: 0
A94: 45665 | B94: 45755 | C94: 45755 | D94: mospin@ext.uber.com | E94: 1270458 | F94: 0 | G94: David rafael Centeno padron | H94: Leonardo Parra Orjuela | I94: US Spa Earner Acc/Pay | J94: Latam U4B Phone Sales Churn13 | K94: Total_Views_Volume | L94: 4 | N94: 4 | O94: #DIV/0!
A95: 45665 | B95: 45755 | C95: 45755 | D95: mospin@ext.uber.com | E95: 1270458 | F95: 0 | G95: David rafael Centeno padron | H95: Leonardo Parra Orjuela | I95: US Spa Earner Acc/Pay | J95: Latam U4B Phone Sales Churn13 | K95: AHT | L95: 0.64 | M95: 0 | O95: #DIV/0!
A96: 45665 | B96: 45755 | C96: 45755 | D96: mospin@ext.uber.com | E96: 1270458 | F96: 0 | G96: David rafael Centeno padron | H96: Leonardo Parra Orjuela | I96: US Spa Earner Acc/Pay | J96: Latam U4B Phone Sales Churn13 | K96: Skips_Percentage | L96: 0 | M96: 104 | N96: 0 | O96: 0
A97: 45665 | B97: 45755 | C97: 45755 | D97: mospin@ext.uber.com | E97: 1270458 | F97: 0 | G97: David rafael Centeno padron | H97: Leonardo Parra Orjuela | I97: US Spa Earner Acc/Pay | J97: Latam U4B Phone Sales Churn13 | K97: Tickets_Solved_Volume | L97: 91 | N97: 91 | O97: #DIV/0!
A98: 45665 | B98: 45755 | C98: 45755 | D98: mospin@ext.uber.com | E98: 1270458 | F98: 0 | G98: David rafael Centeno padron | H98: Leonardo Parra Orjuela | I98: US Spa Earner Acc/Pay | J98: Latam U4B Phone Sales Churn13 | K98: Invalid_Transfers_Percentage | L98: 2100 | M98: 21 | N98: 100 | O98: 100
A99: 45665 | B99: 45755 | C99: 45755 | D99: mospin@ext.uber.com | E99: 1270458 | F99: 0 | G99: David rafael Centeno padron | H99: Leonardo Parra Orjuela | I99: US Spa Earner Acc/Pay | J99: Latam U4B Phone Sales Churn13 | K99: Abandon_Percentage | L99: 0 | M99: 1 | N99: 0 | O99: 0
A100: 45665 | B100: 45755 | C100: 45755 | D100: mospin@ext.uber.com | E100: 1270458 | F100: 0 | G100: David rafael Centeno padron | H100: Leonardo Parra Orjuela | I100: US Spa Earner Acc/Pay | J100: Latam U4B Phone Sales Churn13 | K100: Abandon_Percentage | L100: 0 | M100: 1 | N100: 0 | O100: 0
...

Sheet Historial
A1: Fecha | B1: BMS ID | C1: Nombre Completo | D1: KPI | E1: Valor
A2: 45705.55 | B2: 1270458 | C2: Ospina, Michel | D2: 1_Stars_Percentage | E2: 16
A3: 45705.55 | B3: 1270458 | C3: Ospina, Michel | D3: AHT | E3: 10
A4: 45705.55 | B4: 1270458 | C4: Ospina, Michel | D4: CSAT | E4: 3.67
A5: 45705.55 | B5: 1270458 | C5: Ospina, Michel | D5: Spotcheck | E5: 90
A6: 45705.55 | B6: 1270458 | C6: Ospina, Michel | D6: TPH | E6: 8.5
A7: 45705.662 | B7: 1270458 | C7: Ospina, Michel | D7: 1_Stars_Percentage | E7: 16
A8: 45705.662 | B8: 1270458 | C8: Ospina, Michel | D8: 1_Stars_Percentage | E8: 23
A9: 45705.662 | B9: 1270458 | C9: Ospina, Michel | D9: 1_Stars_Percentage | E9: 16
A10: 45705.662 | B10: 1270458 | C10: Ospina, Michel | D10: AHT | E10: 10
A11: 45705.662 | B11: 1270458 | C11: Ospina, Michel | D11: AHT | E11: 23
A12: 45705.662 | B12: 1270458 | C12: Ospina, Michel | D12: AHT | E12: 10
A13: 45705.662 | B13: 1270458 | C13: Ospina, Michel | D13: CSAT | E13: 3.67
... A52: 45705.662 | B52: 1270458 | C52: Ospina, Michel | D52: TPH | E52: 8.5
A53: 45705.669 | B53: Account Recovery | C53: 1270458 | D53: Ospina, Michel | E53: 1_Stars_Percentage | F53: 0.11
A54: 45705.669 | B54: Account Recovery | C54: 1270458 | D54: Ospina, Michel | E54: AHT | F54: NA
A55: 45705.669 | B55: Account Recovery | C55: 1270458 | D55: Ospina, Michel | E55: CSAT | F55: 4.1
A56: 45705.669 | B56: Account Recovery | C56: 1270458 | D56: Ospina, Michel | E56: Spotcheck | F56: 0.9
A57: 45705.669 | B57: Account Recovery | C57: 1270458 | D57: Ospina, Michel | E57: TPH | F57: 10
A58: 45705.669 | B58: Account Recovery | C58: 1270458 | D58: Ospina, Michel | E58: 1_Stars_Percentage | F58: 0.11
A59: 45705.669 | B59: Account Recovery | C59: 1270458 | D59: Ospina, Michel | E59: AHT | F59: NA
A60: 45705.669 | B60: Account Recovery | C60: 1270458 | D60: Ospina, Michel | E60: CSAT | F60: 4.1
A61: 45705.669 | B61: Account Recovery | C61: 1270458 | D61: Ospina, Michel | E61: Spotcheck | F61: 0.9
A62: 45705.669 | B62: Account Recovery | C62: 1270458 | D62: Ospina, Michel | E62: TPH | F62: 10
A63: 45705.669 | B63: Account Recovery | C63: 1270458 | D63: Ospina, Michel | E63: 1_Stars_Percentage | F63: 0.11
A64: 45705.669 | B64: Account Recovery | C64: 1270458 | D64: Ospina, Michel | E64: AHT | F64: NA
A65: 45705.669 | B65: Account Recovery | C65: 1270458 | D65: Ospina, Michel | E65: CSAT | F65: 4.1
A66: 45705.669 | B66: Account Recovery | C66: 1270458 | D66: Ospina, Michel | E66: Spotcheck | F66: 0.9
A67: 45705.669 | B67: Account Recovery | C67: 1270458 | D67: Ospina, Michel | E67: TPH | F67: 10
A68: 45705.697 | B68: Account Recovery | C68: enero | D68: 1270458 | E68: Ospina, Michel | F68: 1_Stars_Percentage | G68: 0.06
A69: 45705.697 | B69: Account Recovery | C69: enero | D69: 1270458 | E69: Ospina, Michel | F69: AHT | G69: 450
A70: 45705.697 | B70: Account Recovery | C70: enero | D70: 1270458 | E70: Ospina, Michel | F70: CSAT | G70: 4.2
A71: 45705.697 | B71: Account Recovery | C71: enero | D71: 1270458 | E71: Ospina, Michel | F71: Spotcheck | G71: 0.9
A72: 45705.697 | B72: Account Recovery | C72: enero | D72: 1270458 | E72: Ospina, Michel | F72: TPH | G72: NA
A73: 45705.697 | B73: Account Recovery | C73: enero | D73: 1270458 | E73: Ospina, Michel | F73: 1_Stars_Percentage | G73: 0.06
A74: 45705.697 | B74: Account Recovery | C74: enero | D74: 1270458 | E74: Ospina, Michel | F74: AHT | G74: 450
A75: 45705.697 | B75: Account Recovery | C75: enero | D75: 1270458 | E75: Ospina, Michel | F75: CSAT | G75: 4.2
A76: 45705.697 | B76: Account Recovery | C76: enero | D76: 1270458 | E76: Ospina, Michel | F76: Spotcheck | G76: 0.9
A77: 45705.697 | B77: Account Recovery | C77: enero | D77: 1270458 | E77: Ospina, Michel | F77: TPH | G77: NA
A78: 45705.697 | B78: Account Recovery | C78: enero | D78: 1270458 | E78: Ospina, Michel | F78: 1_Stars_Percentage | G78: 0.06
A79: 45705.697 | B79: Account Recovery | C79: enero | D79: 1270458 | E79: Ospina, Michel | F79: AHT | G79: 450
A80: 45705.697 | B80: Account Recovery | C80: enero | D80: 1270458 | E80: Ospina, Michel | F80: CSAT | G80: 4.2
A81: 45705.697 | B81: Account Recovery | C81: enero | D81: 1270458 | E81: Ospina, Michel | F81: Spotcheck | G81: 0.9
A82: 45705.697 | B82: Account Recovery | C82: enero | D82: 1270458 | E82: Ospina, Michel | F82: TPH | G82: NA

Sheet Ruleta
A1: Nombre | B1: KPI
A2: H | B2: E
A3: SD | B3: E
A4: SD | B4: E
A5: SD | B5: E
A6: SD | B6: E
A7: SD | B7: E
A8: SD | B8: E
A9: SD | B9: E
A10: SD | B10: E
A11: SD | B11: E

Sheet Registro
A1: Fecha | B1: LOB | C1: ACCM | D1: Director | E1: H_c | F1: kEY | G1: Score_key_1 | H1: kEY_2 | I1: Score_key_2 | J1: Bonus Structure | K1: KPI_1 | L1: Score_1 | M1: porcentage | N1: KPI_2 | O1: Score_2 | P1: porcentage | Q1: KPI_3 | R1: Score_3 | S1: porcentage | T1: KPI_4 | U1: Score_4 | V1: porcentage | W1: Additional Incentive | X1: KPI_INC_1 | Y1: Score_iNC_1 | Z1: porcentage | AA1: KPI_INC_2 | AB1: Score_iNC_2 | AC1: porcentage | AD1: KPI_INC_3 | AE1: Score_iNC_3 | AF1: porcentage | AG1: Decreased | AH1: KPI_DEC_1 | AI1: Score_DEC_1 | AJ1: porcentage | AK1: KPI_DEC_2 | AL1: Score_DEC_2 | AM1: porcentage | AO1: Roll
A2: Enero | B2: US FNL SPA | C2: Chamorro, Valentina | D2: Ospina, Michel | E2: =COUNTIFS(H_C!B:B, B2, H_C!D:D, "<>Soporte") -> 6 | F2: Abs Jus | G2: <=4% | H2: SHK TK | I2: >6% | K2: Q@U | L2: 0.97 | M2: 0.3 | N2: Routing Errors (Non U4B Cases) | O2: 0 | P2: 0.4 | Q2: Handle time per ticket | R2: <=4 | S2: 0.3 | T2: SHK TK | U2: 6.25 | V2: 0.2 | AH2: AF | AI2: <=1 | AJ2: -1
A5: Enero | B5: US Phone Earner Spa | C5: Chamorro, Valentina | D5: Ospina, Michel | E5: =COUNTIFS(H_C!B:B, B5, H_C!D:D, "<>Soporte") -> 53 | F5: SHK Bliss | G5: <=22% | H5: 0 | I5: 0 | K5: 1_Stars_Percentage | L5: <=5% | M5: 0.4 | N5: AHT Loaded | O5: 7.5 | P5: 0.35 | Q5: Q@U Compliance | R5: >=90% | S5: 0.25 | T5: 0 | U5: 0 | AH5: ABS | AI5: >6% | AJ5: -20 | AK5: AF | AL5: >0 | AM5: -0.5
A6: Enero | B6: US Chat Earner Spa | C6: Chamorro, Valentina | D6: Ospina, Michel | E6: =COUNTIFS(H_C!B:B, B6, H_C!D:D, "<>Soporte") -> 34 | F6: SHK Bliss | G6: <=20% | H6: 0 | I6: 0 | K6: 1_Stars_Percentage | L6: <=4% | M6: 0.4 | N6: AHT Loaded | O6: 10 | P6: 0.3 | Q6: Q@U Compliance | R6: >=90% | S6: 0.3 | T6: 0 | U6: 0 | AH6: ABS | AI6: >6% | AJ6: -20 | AK6: AF | AL6: >0 | AM6: -0.5
A7: Enero | B7: US Cross Support | C7: Chamorro, Valentina | D7: Ospina, Michel | E7: =COUNTIFS(H_C!B:B, B7, H_C!D:D, "<>Soporte") -> 21 | F7: TPH | G7: >9 | H7: ABS | I7: <7% | K7: 1_Stars_Percentage | L7: <=7.5% | M7: 0.4 | N7: Quality@Uber | O7: >=90% | P7: 0.15 | Q7: AHT | R7: <=7.30 | S7: 0.25 | T7: SHK | U7: <=18% | V7: 0.2 | X7: Quality@Uber | Y7: >90 | Z7: 0.05 | AA7: Quality@Uber | AB7: <=10% | AC7: 0.0225 | AD7: 1_Stars_Percentage | AE7: <10 | AF7: 0.05 | AH7: Quality@Uber | AI7: >90 | AJ7: -1 | AK7: 1_Stars_Percentage | AL7: >10 | AM7: 10
A8: Enero | B8: US Phone Earner Diamond | C8: Chamorro, Valentina | D8: Ospina, Michel | E8: =COUNTIFS(H_C!B:B, B8, H_C!D:D, "<>Soporte") -> 39 | F8: Abs Injus | G8: <7% | H8: AF | I8: 0 | K8: 1 Star% | L8: <=8.50% | M8: 0.33 | N8: Compliance Q@U | O8: >=93% | P8: 0.15 | Q8: AHT | R8: <=6.30 | S8: 0.25 | T8: SHK | U8: <=18% | V8: 0.2 | X8: ABS | Y8: 0 | Z8: 0.05 | AA8: TOAST | AB8: <=10% | AC8: 0.0225 | AH8: AF | AI8: >0 | AJ8: -1 | AK8: Compliance Q@U
AH9: SHK Tool | AI9: >=21% | AJ9: -0.15
AJ10: -0.2
AJ11: -0.2
AH12: AF | AI12: >= 1 | AJ12: -0.2
AH13: AF | AI13: >= 1 | AJ13: -0.1 | AK13: Invalid Transfers | AL13: < 20% | AM13: -0.1
AJ14: -0.1 | AK14: Invalid Transfers | AL14: < 20% | AM14: -0.1
A15: Febrero | B15: US Cross Support | C15: Chamorro, Valentina | D15: Ospina, Michel | E15: =COUNTIFS(H_C!B:B, B15, H_C!D:D, "<>Soporte") -> 21 | F15: SHK WF | G15: <=17% | H15: ABS Injus | I15: <=5% | K15: Q@U | L15: >= 90% | M15: 0.3 | N15: 1 Star General% | O15: <= 6.5% | P15: 0.2 | Q15: TPH | R15: >=7.5 | S15: 0.3 | T15: FCR | U15: >=30% | V15: 0.2 | X15: TPH | Y15: >= 9 | Z15: =67107.86/367843 -> 0.18243615 | AA15: Tickets_Solved_Volume | AB15: > 1100 | AC15: =54906.43/367843 -> 0.14926594 | AH15: AF | AI15: >= 1 | AJ15: -0.1 | AK15: Invalid Transfers | AL15: < 20% | AM15: -0.1
J19: Registro: para kEY desde la F a la I Bonus Structure del rango K a la V Additional Incentive del rango X a la AF Decreased AH a la AM, en este para Key esta bien
J20: Registro_pisos: Key, Rango desde la F hasta la L Bonus Structure rango dewde la M hasta la AY Additional Incentive Rango desde la BA hasta la BI Decreased RAANGO BK BV
A21: Febrero | B21: US Call To Ride | C21: Mora, Daniel | D21: Ospina, Michel | F21: Concurrency | G21: <223 | H21: NPV_Percentage | I21: <23 | K21: NPV_Percentage | L21: <23 | M21: 30 | N21: CHT | O21: <=23 | P21: 30 | Q21: AHT | R21: >=23 | S21: 30 | T21: NPV_Percentage | U21: <=23 | V21: 10 | X21: Invalid_Transfers_Percentage | Y21: <23 | Z21: 23 | AH21: DSAT | AI21: <23 | AJ21: 23

Sheet correos
A1: CCMS ID | B1: Name | C1: ACCM | D1: Role | E1: Ext Account | F1: TP Email
A2: 1584677 | B2: Martinez, Wendy | C2: Osorio, Julian | D2: Account Manager | E2: martinez.wendy@ext.uber.com | F2: wendy.martinez@teleperformance.com
A3: 1702877 | B3: Carvajal, Eliana | C3: Castillo, Carlos | D3: Development Assistant Manager | E3: ecarva1@ext.uber.com | F3: eliana.carvajal@teleperformance.com
A4: 1802502 | B4: Rey, Lina | C4: Castillo, Carlos | D4: Sr Operations Manager | E4: lreypa@ext.uber.com | F4: lina.rey@teleperformance.com
A5: 1809093 | B5: Fisco, Ivan | C5: Mora, Cindy | D5: TOPS | E5: - | F5: ivan.fiscolondono@teleperformance.com
A6: 1933493 | B6: Salazar, Samuel | C6: Rodriguez, Moises | D6: ACCM | E6: ssalaz@ext.uber.com | F6: samuel.salazarh@teleperformance.com
A7: 2030733 | B7: Corzo, Fabian | C7: Mejia, Jaime | D7: QA | E7: fcorzo@ext.uber.com | F7: fabian.corzo@teleperformance.co
A8: 2092436 | B8: Parra, Leonardo | C8: Rojas, Maicol | D8: ACCM | E8: lparra1@ext.uber.com | F8: leonardo.parraorjuela@teleperformance.com
A9: 2132347 | B9: Villalba, Diego | C9: Rojas, Jhon | D9: QA | E9: dvilla8@ext.uber.com | F9: diego.villalba@teleperformance.co
A10: 1073048 | B10: Castro, Kelly | C10: Luna, Maria | D10: QA Manager | E10: castro.kelly@ext.uber.com | F10: kelly.castro@teleperformance.com
A11: 828715 | B11: Luis, Yuleidy | C11: Castillo, Carlos | D11: Account Manager | E11: luis.yuleidy@ext.uber.com | F11: yuleidy.luis@teleperformance.com
A12: 1339636 | B12: Cadena, Duvan | C12: Martinez, Wendy | D12: ACCM | E12: dcaden@ext.uber.com | F12: duvan.cadena@teleperformance.com
A13: 1270458 | B13: Ospina, Michel | C13: Chamorro, Valentina | D13: Reporting Analyst | E13: mospin@ext.uber.com | F13: michel.ospina@teleperformance.co
... A313: 3161628 | B313: Colina, Mariangela | C313: Luna, Maria | D313: QA Manager | E313: mcolin2@ext.uber.com | F313: mariangela.colinaalarcon@teleperformance.com

Sheet Usuario
A1: ccmd id | B1: Agent | C1: Ext Account | D1: Roll | E1: LOB | F1: Perfil | G1: Director | H1: Salario | I1: Horas | J1: %salario
A2: 728954 | B2: Londono, Isabel - 8954 | C2: ilondo1@ext.uber.com | D2: Customer Expert | E2: Latam Earner Conversion | F2: Español | G2: =IFERROR(VLOOKUP(A2,H_C!$A$2:$G$2628,7,0),"Validar HC",) -> #N/A | I2: 42 | L2: {=UNIQUE(D1:D4619)} -> Roll
A3: 752718 | B3: Hernandez, Carla - 2718 | C3: cherna85@ext.uber.com | D3: Customer Expert | E3: Earner Conversion Chat | F3: Español | G3: =IFERROR(VLOOKUP(A3,H_C!$A$2:$G$2628,7,0),"Validar HC") -> Soler, Maria | H3: 1623501 | I3: 42 | L3: Customer Expert
A4: 801763 | B4: Ospina, Paula - 1763 | C4: pospin1@ext.uber.com | D4: Customer Expert | E4: Earner Conversion WhatsApp | F4: Español | G4: =IFERROR(VLOOKUP(A4,H_C!$A$2:$G$2628,7,0),"Validar HC") -> Soler, Maria | H4: 1623501 | I4: 42 | N4: 2200286 | O4: =N4*30% -> 660085.8 | P4: =O4*40% -> 264034.32
A5: 951124 | B5: Moreno, Nancy - 1124 | C5: nmoren@ext.uber.com | D5: Customer Expert | E5: Eats Menus Creation | F5: Español | G5: =IFERROR(VLOOKUP(A5,H_C!$A$2:$G$2628,7,0),"Validar HC") -> Garcia, Helmer | H5: 1623501 | I5: 42 | K5: =H5/30% -> 5411670 | L5: 127
A6: 1204240 | B6: GarciaV, Jose - 4240 | C6: jgarci148@ext.uber.com | D6: Customer Expert | E6: US U4B Triage | F6: Español | G6: =IFERROR(VLOOKUP(A6,H_C!$A$2:$G$2628,7,0),"Validar HC") -> Gonzalez, Cristian | H6: 1623501 | I6: 42 | L6: QA
A7: 1289223 | B7: GonzalezR, Fabian - 9223 | C7: fgonza19@ext.uber.com | D7: Customer Expert | E7: Restaurants Ads Sales | F7: Español | G7: =IFERROR(VLOOKUP(A7,H_C!$A$2:$G$2628,7,0),"Validar HC") -> Garcia, Helmer | H7: 1623501 | I7: 42 | L7: WFM Analyst
A8: 1351571 | B8: Linares, Sandra - 1571 | C8: slinar@ext.uber.com | D8: Customer Expert | E8: US U4B Triage | F8: Español | G8: =IFERROR(VLOOKUP(A8,H_C!$A$2:$G$2628,7,0),"Validar HC") -> Gonzalez, Cristian | H8: 1623501 | I8: 42 | L8: Analista de Seguridad
A9: 1780877 | B9: Saenz, Ruby - 0877 | C9: rsaenz@ext.uber.com | D9: Customer Expert | E9: Brazil U4B Triage | F9: Español | G9: =IFERROR(VLOOKUP(A9,H_C!$A$2:$G$2628,7,0),"Validar HC") -> Gonzalez, Cristian | H9: 1623501 | I9: 42 | L9: Sr Operations Manager
A10: 1843950 | B10: Pineda, Manuela - 3950 | C10: mpined19@ext.uber.com | D10: Customer Expert | E10: US Phone Earner Priority | F10: Español | G10: =IFERROR(VLOOKUP(A10,H_C!$A$2:$G$2628,7,0),"Validar HC") -> Rodriguez, Moises | H10: 1623501 | I10: 42 | L10: Trainer | M10: En la hoja Usuario en la colimna A esta el bms id de la sesion, en la b el nombre, en la C esta el correo de la sesion D el roll en la E la LOB, en la hoja Incentivos en la columna C esta la lob y si s igual con la de usuarios debe mostrar la tabla de esa lob imprime en un . log que info tiene de esa lob del rango a a la r
A11: 1924474 | B11: Sanchez, Nancy - 4474 | C11: nsanch29@ext.uber.com | D11: Customer Expert | E11: Latam Eats Courier | F11: Español | G11: =IFERROR(VLOOKUP(A11,H_C!$A$2:$G$2628,7,0),"Validar HC") -> Celi, Juan | H11: 1623501 | I11: 42 | L11: PMO Sales
A12: 1999004 | B12: Munoz, Leivyn - 9004 | C12: lmuoz@ext.uber.com | D12: Customer Expert | E12: Translations | F12: Español | G12: =IFERROR(VLOOKUP(A12,H_C!$A$2:$G$2628,7,0),"Validar HC") -> Garatejo, Natalia | H12: 1623501 | I12: 42 | L12: TOPS
A13: 1999005 | B13: Riano, Wilmer - 9005 | C13: wriao@ext.uber.com | D13: Customer Expert | E13: Translations | F13: Español | G13: =IFERROR(VLOOKUP(A13,H_C!$A$2:$G$2628,7,0),"Validar HC") -> Garatejo, Natalia | H13: 1623501 | I13: 42 | L13: OAM
A14: 2015461 | B14: Alfonso, Jhon - 5461 | C14: jalfon6@ext.uber.com | D14: Customer Expert | E14: U4B Phone Sales | F14: Español | G14: =IFERROR(VLOOKUP(A14,H_C!$A$2:$G$2628,7,0),"Validar HC") -> Gonzalez, Cristian | H14: 1623501 | I14: 42 | L14: WFM Director
A15: 2022938 | B15: OsorioA, Diana - 2938 | C15: dosori@ext.uber.com | D15: Customer Expert | E15: Latam G&R LOM Chat | F15: Español | G15: =IFERROR(VLOOKUP(A15,H_C!$A$2:$G$2628,7,0),"Validar HC") -> Osorio, Julian | H15: 1623501 | I15: 42 | L15: WF Manager
A16: 2030739 | B16: Meneses, Yazmin - 0739 | C16: ymenes@ext.uber.com | D16: Customer Expert | E16: Latam IRT L1L2 | F16: Español | G16: =IFERROR(VLOOKUP(A16,H_C!$A$2:$G$2628,7,0),"Validar HC") -> Martinez, Wendy | H16: 1623501 | I16: 42 | L16: QA Lead
A17: 2096488 | B17: Angel, Diana - 6488 | C17: dangel@ext.uber.com | D17: Customer Expert | E17: Eats Menus Creation | F17: Español | G17: =IFERROR(VLOOKUP(A17,H_C!$A$2:$G$2628,7,0),"Validar HC") -> Garcia, Helmer | H17: 1623501 | I17: 42 | L17: OM
A18: 2116682 | B18: Pinzon, Cindy - 6682 | C18: cpinzo1@ext.uber.com | D18: Customer Expert | E18: US Spa Earner Acc/Pay | F18: Español | G18: =IFERROR(VLOOKUP(A18,H_C!$A$2:$G$2628,7,0),"Validar HC") -> Ospina, Michel | H18: 1600000 | I18: 42 | L18: WFM Assistant Manager
A19: 2116701 | B19: Vargas, Angie - 6701 | C19: avarga40@ext.uber.com | D19: Customer Expert | E19: Soporte | F19: Español | G19: =IFERROR(VLOOKUP(A19,H_C!$A$2:$G$2628,7,0),"Validar HC") -> Parra, Jeimmy | H19: 1623501 | I19: 42 | L19: Development Assistant Manager
A20: 2164857 | B20: Olaya, Judy - 4857 | C20: jolaya5@ext.uber.com | D20: Customer Expert | E20: US U4B Triage | F20: Español | G20: =IFERROR(VLOOKUP(A20,H_C!$A$2:$G$2628,7,0),"Validar HC") -> Gonzalez, Cristian | H20: 1623501 | I20: 42 | L20: Coordinador Nomina | N20: 588000 | O20: 0.3
A21: 2164860 | B21: Sanchez, Karen - 4860 | C21: ksanch2@ext.uber.com | D21: Customer Expert | E21: US Cross Support | F21: Español | G21: =IFERROR(VLOOKUP(A21,H_C!$A$2:$G$2628,7,0),"Validar HC") -> Ospina, Michel | H21: 1623501 | I21: 42 | L21: Sr Training Manager
A22: 2167116 | B22: GomezV, Diana - 7116 | C22: dgomez22@ext.uber.com | D22: Customer Expert | E22: U4B Phone Sales Churn | F22: Español | G22: =IFERROR(VLOOKUP(A22,H_C!$A$2:$G$2628,7,0),"Validar HC") -> Gonzalez, Cristian | H22: 1623501 | I22: 42 | L22: HR Assistant | N22: 2200000 | O22: agente_bi
A23: 2172302 | B23: Villadiego, Joaquin - 2302 | C23: avilla64@ext.uber.com | D23: Customer Expert | E23: Translations | F23: Español | G23: =IFERROR(VLOOKUP(A23,H_C!$A$2:$G$2628,7,0),"Validar HC") -> Garatejo, Natalia | H23: 1623501 | I23: 42 | L23: QA Insights LATAM PSL | N23: 550000 | O23: 0.25
A24: 2185277 | B24: Nino, Andres - 5277 | C24: anino@ext.uber.com | D24: Customer Expert | E24: US U4B Triage | F24: Español | G24: =IFERROR(VLOOKUP(A24,H_C!$A$2:$G$2628,7,0),"Validar HC") -> Gonzalez, Cristian | H24: 1623501 | I24: 42 | L24: HR Coordinator
A25: 2190483 | B25: Arce, Luz - 0483 | C25: larce@ext.uber.com | D25: Customer Expert | E25: LatAm SORT SPA | F25: Español | G25: =IFERROR(VLOOKUP(A25,H_C!$A$2:$G$2628,7,0),"Validar HC") -> Martinez, Wendy | H25: 1623501 | I25: 42 | L25: Global Training Manager | N25: 2200000 | O25: Soporte_bi
A26: 2816053 | B26: Castaneda, Maria - 6053 | C26: mcasta17@ext.uber.com | D26: Customer Expert | E26: US Spa Earner Acc/Pay | F26: Español | G26: =IFERROR(VLOOKUP(A26,H_C!$A$2:$G$2628,7,0),"Validar HC") -> Ospina, Michel | H26: 1600000 | I26: 42 | L26: Business Development Assistant | N26: 550000 | O26: 0.25
A27: 2218922 | B27: Cuervo, Jose - 8922 | C27: jcuerv1@ext.uber.com | D27: Customer Expert | E27: Content Development POR | F27: Español | G27: =IFERROR(VLOOKUP(A27,H_C!$A$2:$G$2628,7,0),"Validar HC") -> Garatejo, Natalia | H27: 1623501 | I27: 42 | L27: WFM Real-Time Analyst
A28: 2225563 | B28: Santos, Yusunguaira - 5563 | C28: fyusun1@ext.uber.com | D28: Customer Expert | E28: Eats Menus EMEA Creation | F28: Español | G28: =IFERROR(VLOOKUP(A28,H_C!$A$2:$G$2628,7,0),"Validar HC") -> Garcia, Helmer | H28: 1623501 | I28: 42 | L28: QA Insights LATAM SSL
A29: 2240540 | B29: Hernandez, Daniela - 0540 | C29: sherna5@ext.uber.com | D29: Customer Expert | E29: Eats Menus Creation | F29: Español | G29: =IFERROR(VLOOKUP(A29,H_C!$A$2:$G$2628,7,0),"Validar HC") -> Garcia, Helmer | H29: 1623501 | I29: 42 | L29: Integrity
A30: 2248847 | B30: Cubillos, Jakeline - 8847 | C30: jcubil1@ext.uber.com | D30: Customer Expert | E30: IRT POR | F30: ingles | G30: =IFERROR(VLOOKUP(A30,H_C!$A$2:$G$2628,7,0),"Validar HC") -> Martinez, Wendy | H30: 1623501 | I30: 42 | L30: Vicepresidente | N30: 1995000 | O30: sup_esp
A31: 2258969 | B31: Riano, Sergio - 8969 | C31: sriano@ext.uber.com | D31: Customer Expert | E31: US Spa Consumer ACC | F31: ingles | G31: =IFERROR(VLOOKUP(A31,H_C!$A$2:$G$2628,7,0),"Validar HC") -> Ospina, Michel | H31: 1623501 | I31: 42 | L31: Development Analyst Sr | N31: $598,500.00. | O31: 0.3
A32: 2259318 | B32: Rosero, Cesar - 9318 | C32: croser@ext.uber.com | D32: Customer Expert | E32: US Phone Earner Spa | F32: ingles | G32: =IFERROR(VLOOKUP(A32,H_C!$A$2:$G$2628,7,0),"Validar HC") -> Ospina, Michel | H32: 1623501 | I32: 42 | L32: WFM Analyst
A33: 2269452 | B33: Arboleda, Juan - 9452 | C33: jarbol3@ext.uber.com | D33: Customer Expert | E33: Eats Phone US LO | F33: ingles | G33: =IFERROR(VLOOKUP(A33,H_C!$A$2:$G$2628,7,0),"Validar HC") -> Soler, Maria | H33: 1623501 | I33: 42 | L33: Trainer Manager | N33: 1400000 | O33: agente_esp
A34: 2269729 | B34: Cortes, Joan - 9729 | C34: jcorte7@ext.uber.com | D34: Customer Expert | E34: US Call To Ride | F34: ingles | G34: =IFERROR(VLOOKUP(A34,H_C!$A$2:$G$2628,7,0),"Validar HC") -> Ospina, Michel | H34: 1623501 | I34: 42 | L34: Trainer Lead | N34: $420,000.00. | O34: 0.3
A35: 2275797 | B35: GonzalezG, Andrea - 5797 | C35: agonza23@ext.uber.com | D35: Customer Expert | E35: US Phone Earner Spa | F35: ingles | G35: =IFERROR(VLOOKUP(A35,H_C!$A$2:$G$2628,7,0),"Validar HC") -> Ospina, Michel | H35: 1623501 | I35: 42 | L35: Support Analyst
A36: 2282732 | B36: Escobar, Yojana - 2732 | C36: yescob2@ext.uber.com | D36: Customer Expert | E36: ENG Growth | F36: ingles | G36: =IFERROR(VLOOKUP(A36,H_C!$A$2:$G$2628,7,0),"Validar HC") -> Soler, Maria | H36: 1623501 | I36: 42 | L36: Reporting Coordinator | N36: 1400000 | O36: Soporte_esp
A37: 2292985 | B37: Garcia, Eddward - 2985 | C37: egarci19@ext.uber.com | D37: Customer Expert | E37: US Phone U4B | F37: ingles | G37: =IFERROR(VLOOKUP(A37,H_C!$A$2:$G$2628,7,0),"Validar HC") -> Gonzalez, Cristian | H37: 1623501 | I37: 42 | L37: WF Director Jr | N37: $420,000.00. | O37: 0.3
A38: 2306026 | B38: Vaquiro, Xiomara - 6026 | C38: xvaqui@ext.uber.com | D38: Customer Expert | E38: Restaurants Ads Sales | F38: ingles | G38: =IFERROR(VLOOKUP(A38,H_C!$A$2:$G$2628,7,0),"Validar HC") -> Garcia, Helmer | H38: 1623501 | I38: 42 | L38: Development Manager
A39: 2307854 | B39: Betancur, Beatriz - 7854 | C39: bbetan@ext.uber.com | D39: Customer Expert | E39: Brazil U4B Triage | F39: ingles | G39: =IFERROR(VLOOKUP(A39,H_C!$A$2:$G$2628,7,0),"Validar HC") -> Gonzalez, Cristian | H39: 1623501 | I39: 42 | L39: Global IT Manager
A40: 2384414 | B40: Espinosa, Leidy - 4414 | C40: lespin8@ext.uber.com | D40: Customer Expert | E40: Eats Phone Restaurants LatAm | F40: ingles | G40: =IFERROR(VLOOKUP(A40,H_C!$A$2:$G$2628,7,0),"Validar HC") -> Celi, Juan | H40: 1623501 | I40: 42 | L40: QA Manager
A41: 2430545 | B41: Parra, Maritza - 0545 | C41: mparra5@ext.uber.com | D41: Customer Expert | E41: IRT POR | F41: ingles | G41: =IFERROR(VLOOKUP(A41,H_C!$A$2:$G$2628,7,0),"Validar HC") -> Martinez, Wendy | H41: 1623501 | I41: 42 | L41: Reporting Analyst
A42: 2452237 | B42: Quijano, Cristian - 2237 | C42: cquija@ext.uber.com | D42: Customer Expert | E42: Latam Uber Flash | F42: ingles | G42: =IFERROR(VLOOKUP(A42,H_C!$A$2:$G$2628,7,0),"Validar HC") -> Martinez, Wendy | H42: 1623501 | I42: 42 | L42: Audit
A43: 2455514 | B43: Castrillon, Yohan - 5514 | C43: ycastr1@ext.uber.com | D43: Customer Expert | E43: Brazil U4B Triage | F43: ingles | G43: =IFERROR(VLOOKUP(A43,H_C!$A$2:$G$2628,7,0),"Validar HC") -> Gonzalez, Cristian | H43: 1623501 | I43: 42 | L43: Senior Analyst Payroll
A44: 2570479 | B44: Varela, Jessica - 0479 | C44: jvarel2@ext.uber.com | D44: Customer Expert | E44: Latam Eats Eater | F44: ingles | G44: =IFERROR(VLOOKUP(A44,H_C!$A$2:$G$2628,7,0),"Validar HC") -> Celi, Juan | H44: 1623501 | I44: 42 | L44: Psychologist
A45: 2587731 | B45: Chaparro, Neila - 7731 | C45: nchapa1808@ext.uber.com | D45: Customer Expert | E45: LatAm IIT | F45: ingles | G45: =IFERROR(VLOOKUP(A45,H_C!$A$2:$G$2628,7,0),"Validar HC") -> Martinez, Wendy | H45: 1623501 | I45: 42 | L45: Improvement Sr Analyst
A46: 2621136 | B46: Castano, Lina - 1136 | C46: lcasta20@ext.uber.com | D46: Customer Expert | E46: US Email Driver Eats CX Spa | F46: ingles | G46: =IFERROR(VLOOKUP(A46,H_C!$A$2:$G$2628,7,0),"Validar HC") -> Soler, Maria | H46: 1623501 | I46: 42 | L46: Reporting Manager
A47: 2634994 | B47: Mendez, Martha - 4994 | C47: mmende40@ext.uber.com | D47: Customer Expert | E47: Earner Conversion Chat | F47: ingles | G47: =IFERROR(VLOOKUP(A47,H_C!$A$2:$G$2628,7,0),"Validar HC") -> Soler, Maria | H47: 1623501 | I47: 42 | L47: POC Nomina
A48: 2644855 | B48: Gomez, Luisa - 4855 | C48: lgomez28@ext.uber.com | D48: Customer Expert | E48: US Cross Support | F48: ingles | G48: =IFERROR(VLOOKUP(A48,H_C!$A$2:$G$2628,7,0),"Validar HC") -> Ospina, Michel | H48: 1623501 | I48: 42 | L48: Development Analyst Jr
A49: 2704721 | B49: Baron, Diana - 4721 | C49: dbaron5@ext.uber.com | D49: Customer Expert | E49: US Chat Earner Spa | F49: ingles | G49: =IFERROR(VLOOKUP(A49,H_C!$A$2:$G$2628,7,0),"Validar HC") -> Ospina, Michel | H49: 1623501 | I49: 42 | L49: Technical Account Manager
... A54: 2987885 | B54: Espitia, Paula - 7885 | C54: pespit1@ext.uber.com | D54: Customer Expert | E54: Mexico Receipt Support | F54: ingles | G54: =IFERROR(VLOOKUP(A54,H_C!$A$2:$G$2628,7,0),"Validar HC") -> Ayala, Giselle | H54: 1623501 | I54: 42 | L54: Project Manager
A55: 3024170 | B55: Garcia, Mally - 4170 | C55: mgarci178@ext.uber.com | D55: Customer Expert | E55: LatAm SORT SPA | F55: ingles | G55: =IFERROR(VLOOKUP(A55,H_C!$A$2:$G$2628,7,0),"Validar HC") -> Martinez, Wendy | H55: 1623501 | I55: 42
A56: 3046244 | B56: Fernandez, Javier - 6244 | C56: jferna33@ext.uber.com | D56: Customer Expert | E56: US Freight Carrier Inbound | F56: ingles | G56: =IFERROR(VLOOKUP(A56,H_C!$A$2:$G$2628,7,0),"Validar HC") -> Soler, Maria | H56: 1623501 | I56: 42
A57: 3050288 | B57: Ferrucho, Alejandra - 0288 | C57: aferru@ext.uber.com | D57: Customer Expert | E57: Latam Consumer Off Trip EM | F57: ingles | G57: =IFERROR(VLOOKUP(A57,H_C!$A$2:$G$2628,7,0),"Validar HC") -> Ayala, Giselle | H57: 1623501 | I57: 42
A58: 3052449 | B58: Lindarte, Carlos - 2449 | C58: clinda@ext.uber.com | D58: Customer Expert | E58: U4B Phone Sales Churn | F58: ingles | G58: =IFERROR(VLOOKUP(A58,H_C!$A$2:$G$2628,7,0),"Validar HC") -> Gonzalez, Cristian | H58: 1623501 | I58: 42
A59: 3053672 | B59: Hernandez, Yiseth - 3672 | C59: yherna8@ext.uber.com | D59: Customer Expert | E59: EMEA Portugal Rider | F59: ingles | G59: =IFERROR(VLOOKUP(A59,H_C!$A$2:$G$2628,7,0),"Validar HC") -> Martinez, Wendy | H59: 1623501 | I59: 42
A60: 3061299 | B60: Vanegas, Yuli - 1299 | C60: yvaneg2@ext.uber.com | D60: Customer Expert | E60: US Email Driver Eats CX Spa | F60: ingles | G60: =IFERROR(VLOOKUP(A60,H_C!$A$2:$G$2628,7,0),"Validar HC") -> Soler, Maria | H60: 1623501 | I60: 42
A61: 3066276 | B61: Caballero, Ana - 6276 | C61: acabal7@ext.uber.com | D61: Customer Expert | E61: Mexico Receipt Support | F61: ingles | G61: =IFERROR(VLOOKUP(A61,H_C!$A$2:$G$2628,7,0),"Validar HC") -> Ayala, Giselle | H61: 1623501 | I61: 42
A62: 3070802 | B62: Leguizamon, Jhon - 0802 | C62: jlegui3@ext.uber.com | D62: Customer Expert | E62: Latam IRT L1L2 | F62: ingles | G62: =IFERROR(VLOOKUP(A62,H_C!$A$2:$G$2628,7,0),"Validar HC") -> Martinez, Wendy | H62: 1623501 | I62: 42
A63: 3070804 | B63: Usaquen, Diana - 0804 | C63: dusaqu@ext.uber.com | D63: Customer Expert | E63: Eats Menus Groceries | F63: ingles | G63: =IFERROR(VLOOKUP(A63,H_C!$A$2:$G$2628,7,0),"Validar HC") -> Garcia, Helmer | H63: 1623501 | I63: 42
A64: 3070810 | B64: Quintero, Leslie - 0810 | C64: lquint6@ext.uber.com | D64: Customer Expert | E64: Eats Menus Portugal | F64: ingles | G64: =IFERROR(VLOOKUP(A64,H_C!$A$2:$G$2628,7,0),"Validar HC") -> Garcia, Helmer | H64: 1623501 | I64: 42
A65: 3070813 | B65: Reyes, Luceli - 0813 | C65: lreyes9@ext.uber.com | D65: Customer Expert | E65: Eats Menus Creation | F65: ingles | G65: =IFERROR(VLOOKUP(A65,H_C!$A$2:$G$2628,7,0),"Validar HC") -> Garcia, Helmer | H65: 1623501 | I65: 42
A66: 3070828 | B66: Martinez, Yenny - 0828 | C66: ymarti4@ext.uber.com | D66: Customer Expert | E66: Eats Menus Groceries | F66: ingles | G66: =IFERROR(VLOOKUP(A66,H_C!$A$2:$G$2628,7,0),"Validar HC") -> Garcia, Helmer | H66: 1623501 | I66: 42
... A1481: 5546185 | B1481: Salinas, Juan - 6185 | C1481: jsalin15@ext.uber.com | D1481: Customer Expert | E1481: US Cross Support | F1481: ingles | G1481: =IFERROR(VLOOKUP(A1481,H_C!$A$2:$G$2628,7,0),"Validar HC") -> Ospina, Michel | H1481: 1623501 | I1481: 42
A1482: 5546192 | B1482: Cortes, Daniel - 6192 | C1482: dcorte29@ext.uber.com | D1482: Customer Expert | E1482: US Cross Support | F1482: ingles | G1482: =IFERROR(VLOOKUP(A1482,H_C!$A$2:$G$2628,7,0),"Validar HC") -> Ospina, Michel | H1482: 1623501 | I1482: 42 | J1482: =H1482*30 -> 48705030 | K1482: =J1482*30% -> 14611509
A1483: 5546239 | B1483: Herrera, Laura - 6239 | C1483: lherre35@ext.uber.com | D1483: Customer Expert | E1483: US Cross Support | F1483: ingles | G1483: =IFERROR(VLOOKUP(A1483,H_C!$A$2:$G$2628,7,0),"Validar HC") -> Ospina, Michel | H1483: 1623501 | I1483: 42
A1484: 5546273 | B1484: Angulo, Karent - 6273 | C1484: kangul2@ext.uber.com | D1484: Customer Expert | E1484: US Spa Consumer ACC | F1484: ingles | G1484: =IFERROR(VLOOKUP(A1484,H_C!$A$2:$G$2628,7,0),"Validar HC") -> Ospina, Michel | H1484: 1623501 | I1484: 42
A1486: 5546275 | B1486: Malagon, Leidy - 6275 | C1486: lmalag2@ext.uber.com | D1486: Customer Expert | E1486: US Phone Earner Spa | F1486: ingles | G1486: =IFERROR(VLOOKUP(A1486,H_C!$A$2:$G$2628,7,0),"Validar HC") -> Ospina, Michel | H1486: 1623501 | I1486: 42
A1487: 5546277 | B1487: Avendano, Angie - 6277 | C1487: aavend8@ext.uber.com | D1487: Customer Expert | E1487: US Phone Earner Spa | F1487: ingles | G1487: =IFERROR(VLOOKUP(A1487,H_C!$A$2:$G$2628,7,0),"Validar HC") -> Ospina, Michel | H1487: 1623501 | I1487: 42
A1488: 5546279 | B1488: Briceno, Wilka - 6279 | C1488: wbrice@ext.uber.com | D1488: Customer Expert | E1488: US Spa Consumer ACC | F1488: ingles | G1488: =IFERROR(VLOOKUP(A1488,H_C!$A$2:$G$2628,7,0),"Validar HC") -> Ospina, Michel | H1488: 1623501 | I1488: 42
A1489: 5549463 | B1489: Rojas, Jose - 9463 | C1489: jrojas74@ext.uber.com | D1489: Customer Expert | E1489: US Call To Ride | F1489: ingles | G1489: =IFERROR(VLOOKUP(A1489,H_C!$A$2:$G$2628,7,0),"Validar HC") -> Ospina, Michel | H1489: 1623501 | I1489: 42
A1490: 5549466 | B1490: Marentes, Leidy - 9466 | C1490: lmaren@ext.uber.com | D1490: Customer Expert | E1490: US Phone Eng VS | F1490: ingles | G1490: =IFERROR(VLOOKUP(A1490,H_C!$A$2:$G$2628,7,0),"Validar HC") -> Ospina, Michel | H1490: 1623501 | I1490: 42
A1491: 5549482 | B1491: Orozco, Jeronimo - 9482 | C1491: jorozc14@ext.uber.com | D1491: Customer Expert | E1491: US Phone U4B Transit | F1491: ingles | G1491: =IFERROR(VLOOKUP(A1491,H_C!$A$2:$G$2628,7,0),"Validar HC") -> Gonzalez, Cristian | H1491: 1623501 | I1491: 42
A1492: 5549700 | B1492: Chaparro, Bibian - 9700 | C1492: bchapa@ext.uber.com | D1492: Customer Expert | E1492: EMEA Ads Sales | F1492: ingles | G1492: =IFERROR(VLOOKUP(A1492,H_C!$A$2:$G$2628,7,0),"Validar HC") -> Garcia, Helmer | H1492: 1623501 | I1492: 42
A1493: 5549704 | B1493: Achury, Nycold - 9704 | C1493: nachur@ext.uber.com | D1493: Customer Expert | E1493: Restaurants Ads Sales | F1493: ingles | G1493: =IFERROR(VLOOKUP(A1493,H_C!$A$2:$G$2628,7,0),"Validar HC") -> Garcia, Helmer | H1493: 1623501 | I1493: 42
A1494: 5550642 | B1494: LopezM, Juliana - 0642 | C1494: jlopez217@ext.uber.com | D1494: Customer Expert | E1494: US U4B Triage | F1494: ingles | G1494: =IFERROR(VLOOKUP(A1494,H_C!$A$2:$G$2628,7,0),"Validar HC") -> Gonzalez, Cristian | H1494: 1623501 | I1494: 42
A1495: 5552065 | B1495: OrozcoS, Samuel - 2065 | C1495: sorozc7@ext.uber.com | D1495: Customer Expert | E1495: Eats Phone US LO | F1495: ingles | G1495: =IFERROR(VLOOKUP(A1495,H_C!$A$2:$G$2628,7,0),"Validar HC") -> Soler, Maria | H1495: 1623501 | I1495: 42
... A2346: 5778673 | B2346: Celis, Maria - 8673 | C2346: mcelis2@ext.uber.com | D2346: Customer Expert | E2346: Latam G&R LOM Chat | F2346: ingles | G2346: =IFERROR(VLOOKUP(A2346,H_C!$A$2:$G$2628,7,0),"Validar HC") -> Osorio, Julian | H2346: 2200286 | I2346: 42
A2347: 5618619 | B2347: Rincon, David - 8619 | C2347: drinco14@ext.uber.com | D2347: 127 | E2347: Latam G&R LOM Chat | F2347: ingles | G2347: =IFERROR(VLOOKUP(A2347,H_C!$A$2:$G$2628,7,0),"Validar HC") -> Osorio, Julian | H2347: 2200286 | I2347: 42
A2348: 5709731 | B2348: Zambrano, Jordan De Jesus - 9731 | C2348: jzambr8@ext.uber.com | D2348: Customer Expert | E2348: Latam G&R LOM Chat | F2348: ingles | G2348: =IFERROR(VLOOKUP(A2348,H_C!$A$2:$G$2628,7,0),"Validar HC") -> Osorio, Julian | H2348: 2200286 | I2348: 42
A2349: 5879174 | B2349: Valeriano, Mariana - 9174 | C2349: mvaler8@ext.uber.com | D2349: Customer Expert | E2349: Latam G&R LOM Chat | F2349: ingles | G2349: =IFERROR(VLOOKUP(A2349,H_C!$A$2:$G$2628,7,0),"Validar HC") -> Osorio, Julian | H2349: 2200286 | I2349: 42
A2350: 5618617 | B2350: Rodriguez, Daniel - 8617 | C2350: drodri148@ext.uber.com | D2350: Customer Expert | E2350: Latam G&R LOM Chat | F2350: ingles | G2350: =IFERROR(VLOOKUP(A2350,H_C!$A$2:$G$2628,7,0),"Validar HC") -> Osorio, Julian | H2350: 2200286 | I2350: 42
A2351: 6019104 | B2351: Usaquen, Jhoan - 9104 | C2351: jusaqu@ext.uber.com | D2351: Customer Expert | E2351: Latam G&R Chat | F2351: ingles | G2351: =IFERROR(VLOOKUP(A2351,H_C!$A$2:$G$2628,7,0),"Validar HC") -> Ayala, Giselle | H2351: 2200286 | I2351: 42
A2352: 6019101 | B2352: Zapata, Juanita - 9101 | C2352: jpardo19@ext.uber.com | D2352: Customer Expert | E2352: Latam G&R LOM Chat | F2352: ingles | G2352: =IFERROR(VLOOKUP(A2352,H_C!$A$2:$G$2628,7,0),"Validar HC") -> Osorio, Julian | H2352: 2200286 | I2352: 42
A2353: 6019133 | B2353: Arbelaez, Tatiana - 9133 | C2353: tarbel1@ext.uber.com | D2353: Customer Expert | E2353: Latam G&R LOM Chat | F2353: ingles | G2353: =IFERROR(VLOOKUP(A2353,H_C!$A$2:$G$2628,7,0),"Validar HC") -> Osorio, Julian | H2353: 2200286 | I2353: 42
A2354: 6019136 | B2354: Gonzalez, Gustavo - 9136 | C2354: ggonza45@ext.uber.com | D2354: Customer Expert | E2354: Latam G&R Chat | F2354: ingles | G2354: =IFERROR(VLOOKUP(A2354,H_C!$A$2:$G$2628,7,0),"Validar HC") -> Ayala, Giselle | H2354: 2200286 | I2354: 42
A2355: 6019139 | B2355: Mendez, Jhonatan - 9139 | C2355: jmende66@ext.uber.com | D2355: Customer Expert | E2355: Latam G&R LOM Chat | F2355: ingles | G2355: =IFERROR(VLOOKUP(A2355,H_C!$A$2:$G$2628,7,0),"Validar HC") -> Osorio, Julian | H2355: 2200286 | I2355: 42
A2356: 6019103 | B2356: Soche, Allison - 9103 | C2356: asoche@ext.uber.com | D2356: Customer Expert | E2356: Driver Payments | F2356: ingles | G2356: =IFERROR(VLOOKUP(A2356,H_C!$A$2:$G$2628,7,0),"Validar HC") -> Garatejo, Natalia | H2356: 2200286 | I2356: 42
A2357: 6019197 | B2357: Zaraza, Thifany - 9197 | C2357: tzaraz@ext.uber.com | D2357: Customer Expert | E2357: Latam G&R Chat | F2357: ingles | G2357: =IFERROR(VLOOKUP(A2357,H_C!$A$2:$G$2628,7,0),"Validar HC") -> Ayala, Giselle | H2357: 2200286 | I2357: 42
A2358: 6019134 | B2358: Camargo, Jose - 9134 | C2358: jcamar32@ext.uber.com | D2358: Customer Expert | E2358: Latam G&R LOM Chat | F2358: ingles | G2358: =IFERROR(VLOOKUP(A2358,H_C!$A$2:$G$2628,7,0),"Validar HC") -> Osorio, Julian | H2358: 2200286 | I2358: 42
A2359: 6019102 | B2359: Cogollo, Katerine - 9102 | C2359: kcogol1@ext.uber.com | D2359: Customer Expert | E2359: Latam Growth Spenders | F2359: ingles | G2359: =IFERROR(VLOOKUP(A2359,H_C!$A$2:$G$2628,7,0),"Validar HC") -> Ayala, Giselle | H2359: 2200286 | I2359: 42
... A2609: 4984021 | B2609: Otavo, Kimberly - 4021 | C2609: - | D2609: Customer Expert | E2609: LatAm IIT | F2609: ingles | G2609: =IFERROR(VLOOKUP(A2609,H_C!$A$2:$G$2628,7,0),"Validar HC") -> Sanchez, Adrian | H2609: 2200286 | I2609: 42
A2610: 623312 | B2610: Lizarazo, Ivon | C2610: ilizar@ext.uber.com | D2610: QA | F2610: ingles | G2610: =IFERROR(VLOOKUP(A2610,H_C!$A$2:$G$2628,7,0),"Validar HC") -> Validar HC | H2610: 2200286 | I2610: 42
A2611: 664043 | B2611: Ovalle, Edgar | C2611: ovalle.edgar@ext.uber.com | D2611: QA | F2611: ingles | G2611: =IFERROR(VLOOKUP(A2611,H_C!$A$2:$G$2628,7,0),"Validar HC") -> Validar HC | H2611: 2200286 | I2611: 42
A2612: 690890 | B2612: Acosta, Oscar | C2612: oacost1@ext.uber.com | D2612: WFM Analyst | F2612: ingles | G2612: =IFERROR(VLOOKUP(A2612,H_C!$A$2:$G$2628,7,0),"Validar HC") -> Validar HC | H2612: 2200286 | I2612: 42
A2613: 828713 | B2613: Diaz, Maria | C2613: mdiaz70@ext.uber.com | D2613: Analista de Seguridad | F2613: ingles | G2613: =IFERROR(VLOOKUP(A2613,H_C!$A$2:$G$2628,7,0),"Validar HC") -> Validar HC | H2613: 2200286 | I2613: 42
A2614: 828715 | B2614: Luis, Yuleidy | C2614: luis.yuleidy@ext.uber.com | D2614: Sr Operations Manager | F2614: ingles | G2614: =IFERROR(VLOOKUP(A2614,H_C!$A$2:$G$2628,7,0),"Validar HC") -> Validar HC | H2614: 2200286 | I2614: 42
A2615: 851996 | B2615: Alonso, Edinson | C2615: efuent12@ext.uber.com | D2615: Trainer | F2615: ingles | G2615: =IFERROR(VLOOKUP(A2615,H_C!$A$2:$G$2628,7,0),"Validar HC") -> Validar HC | H2615: 2200286 | I2615: 42
A2616: 898569 | B2616: Baquero, Harold | C2616: hbaque@ext.uber.com | D2616: PMO Sales | F2616: ingles | G2616: =IFERROR(VLOOKUP(A2616,H_C!$A$2:$G$2628,7,0),"Validar HC") -> Validar HC | H2616: 2200286 | I2616: 42
A2617: 930645 | B2617: Cantor, Sonia | C2617: - | D2617: TOPS | F2617: ingles | G2617: =IFERROR(VLOOKUP(A2617,H_C!$A$2:$G$2628,7,0),"Validar HC") -> Validar HC | H2617: 2200286 | I2617: 42
A2618: 985835 | B2618: Bermudez, Viviana | C2618: vbermu@ext.uber.com | D2618: WFM Analyst | F2618: ingles | G2618: =IFERROR(VLOOKUP(A2618,H_C!$A$2:$G$2628,7,0),"Validar HC") -> Validar HC | H2618: 2200286 | I2618: 42
...

Sheet Configuracion
A1: Mes | B1: OM | C1: LOB | D1: Salario_Base | E1: %_Bono | F1: timet | G1: PVE | J1: Salario | K1: 1600000
A2: Enero | B2: Ospina, Michel | C2: US FNL SPA | D2: 1623501 | E2: 30 | G2: 6000000
A3: Enero | B3: Ospina, Michel | C3: US Spa Earner Acc/Pay | D3: 1600000 | E3: 30 | G3: 6000000 | J3: 0.3 | K3: =K1*J3 -> 480000
A5: Enero | B5: Ospina, Michel | C5: US Phone Earner Spa | D5: 1500000 | E5: 30 | F5: 45998.378 | G5: 6000000
A6: Enero | B6: Ospina, Michel | C6: US Chat Earner Spa | D6: 1423500 | E6: 15 | G6: 6000000
A7: Enero | B7: Ospina, Michel | C7: US Cross Support | D7: 1500000 | E7: 30 | F7: 45998.404 | G7: 6000000
A8: Enero | B8: Ospina, Michel | C8: US Phone Earner Diamond | D8: 2000000 | E8: 30 | G8: 6000000 | J8: KPI | K8: Score | L8: % | N8: % Participación
A9: Febrero | B9: Ospina, Michel | C9: US Call To Ride | D9: 2000000 | E9: 25 | F9: 46040.727 | J9: Quality@Uber | K9: >= 90% | L9: 0.3 | M9: =K$3*L9 -> 144000 | N9: 0.5 | O9: =M$9*N9 -> 72000 | P9: Si el agente tiene 92 se paga 72.000,00
A10: Febrero | B10: Ospina, Michel | C10: Eats Phone US LO | D10: 1600000 | E10: 30 | F10: 46042.657 | J10: Quality@Uber | K10: >= 92% | L10: 0.3 | N10: 0.8 | O10: =M$9*N10 -> 115200
J11: Quality@Uber | K11: >= 95% | L11: 0.3 | N11: 1 | O11: =M$9*N11 -> 144000
J12: 1_Stars_Percentage | K12: <=10 | L12: 0.4 | M12: =K$3*L12 -> 192000 | N12: 0.8 | O12: =M$12*N12 -> 153600
J13: 1_Stars_Percentage | K13: <=7% | L13: 0.4 | N13: 0.9 | O13: =M$12*N13 -> 172800
J14: 1_Stars_Percentage | K14: <=5% | L14: 0.4 | N14: 1 | O14: =M$12*N14 -> 192000 | P14: Si el agente tiene 4.5 se paga 192000
M15: =SUM(M9:M14) -> 336000 | O15: Solo se suma los valore ede 100% y ese es la suma del 30 % o x del salario

Sheet Pivot Table 1
E2: =B2/C2 -> #DIV/0! | H2: 1 | I2: Diaz, Laura - 9922 | J2: 20000 | K2: consumer | M2: Diaz, Laura - 9922 | N2: 4349922 | O2: US Spa Consumer ACC
D3: =C3/B3 -> #VALUE! | I3: Fagua, Lizeth - 3696 | K3: fnl | M3: Fagua, Lizeth - 3696 | N3: 5333696 | O3: US FNL SPA
I4: Ballesteros, Jose - 5112 | K4: consumer | M4: Ballesteros, Jose - 5112 | N4: 4835112 | O4: US Spa Consumer ACC
I5: Camacho, Danna - 1481 | J5: 2000 | K5: fnl | M5: Camacho, Danna - 1481 | N5: 5021481 | O5: US Spa Earner Acc/Pay
I6: Rodriguez, Jesus - 0014 | J6: 20000 | K6: consumer | M6: Rodriguez, Jesus - 0014 | N6: 4980014 | O6: US Spa Consumer ACC
I7: Fagua, Lizeth - 3696 | K7: fnl | M7: Fagua, Lizeth - 3696 | N7: 5333696 | O7: US FNL SPA
I14: 1s Ibito, Laura - 4615
I15: 2s Omana, Juan - 196
I16: 3s GarciaO, Juan - 1414
I18: Maps CX:
I19: 1S Lagos, David - 1561
I20: 2S Barrero, Javier - 6163
I21: 3S CortesC, Daniel - 8887

Sheet Disputa
A1: Fecha Disputa | B1: BMS ID | C1: Nombre | D1: LOB | E1: Fecha KPI | F1: Total Bono | G1: Comentario | H1: Estado | I1: Usuario que Disputa | J1: Correo Usuario
A2: 45965.805 | B2: 4364806 | C2: SanchezC, Natalia - 4806 | D2: US Cross Support | E2: Septiembre | F2: 330035.1 | G2: sdf | H2: Pendiente | I2: mikenet11@gmail.com | J2: mikenet11@gmail.com
A3: 45965.805 | B3: 5320995 | C3: Zamorano, Kevin - 0995 | D3: US Cross Support | E3: Septiembre | F3: -330042.9 | G3: sdf | H3: ✅ Aprobada | I3: mikenet11@gmail.com | J3: mikenet11@gmail.com
A4: 45965.805 | B4: 5296788 | C4: Acevedo, Yuly - 6788 | D4: US Cross Support | E4: Septiembre | F4: 6732875.2 | G4: hpñaas | H4: Pendiente | I4: mikenet11@gmail.com | J4: mikenet11@gmail.com
A5: 45966.646 | B5: 5296788 | C5: Acevedo, Yuly - 6788 | D5: US Cross Support | E5: Septiembre | F5: 6732875.2 | G5: HOLAAA | H5: Pendiente | I5: mikenet11@gmail.com | J5: mikenet11@gmail.com
A6: 45967.365 | B6: 5320995 | C6: Zamorano, Kevin - 0995 | D6: US Cross Support | E6: Enero | F6: 330042.9 | G6: sdfsdfsdfsdfsdfsdfsdfsdf | H6: Pendiente | I6: Ospina, Michel | J6: mikenet11@gmail.com
A7: 45967.365 | B7: 5872088 | C7: Munoz, Marlon - 2088 | D7: US Cross Support | E7: Enero | F7: 198025.74 | G7: sdfsdfsfdsdfsdf | H7: Pendiente | I7: Ospina, Michel | J7: mikenet11@gmail.com
A8: 45967.365 | B8: 2164860 | C8: Sanchez, Karen - 4860 | D8: US Cross Support | E8: Enero | F8: 0 | G8: sdfsdfsdf | H8: ❌ Rechazada | I8: Ospina, Michel | J8: mikenet11@gmail.com
A9: 45967.366 | B9: 5546192 | C9: Cortes, Daniel - 6192 | D9: US Cross Support | E9: Enero | F9: 528068.64 | G9: dfg | H9: ❌ Rechazada | I9: Ospina, Michel | J9: mikenet11@gmail.com
A10: 45967.366 | B10: 5388841 | C10: Guzman, Paula - 8841 | D10: US Cross Support | E10: Enero | F10: 330042.9 | G10: dfg | H10: Pendiente | I10: Ospina, Michel | J10: mikenet11@gmail.com
A11: 45967.366 | B11: 4364806 | C11: SanchezC, Natalia - 4806 | D11: US Cross Support | E11: Enero | F11: 198021.06 | G11: dfg | H11: Pendiente | I11: Ospina, Michel | J11: mikenet11@gmail.com
A12: 46045.812 | B12: 5021467 | C12: Ortega, Ana - 1467 | D12: US Spa Earner Acc/Pay | E12: Febrero | F12: 144000 | G12: este es disputa | H12: Pendiente | I12: Mikenet11 | J12: mikenet11@gmail.com
A13: 46045.815 | B13: 5327776 | C13: Estupinan, Alex - 7776 | D13: US Spa Earner Acc/Pay | E13: Febrero | F13: 307200 | G13: erer | H13: Pendiente | I13: Mikenet11 | J13: mikenet11@gmail.com
... A18: 25568.667 | B18: 5349465 | C18: Diaz, Nicolas - 9465 | D18: US Spa Earner Acc/Pay | E18: Febrero | F18: 0 | G18: si gana jhjkhkjhkjhk | H18: Pendiente | I18: Mikenet11 | J18: mikenet11@gmail.com

Sheet Audit
A1: BMS ID | B1: Nombre Agente | C1: LOB | D1: Role | E1: Supervisor | F1: ACCM | G1: OM | H1: Roll | I1: Bono Aprobado | J1: Fecha Aprobación | K1: Usuario Aprobador | L1: Correo Aprobador | M1: Fecha KPI | N1: Mes CDM | O1: Estado

Sheet Historico_MAX

Sheet incentivos
A1: Fecha_registro | B1: Mes_estructura | C1: kpi | D1: ccms id | E1: Nombre | F1: LOB | K1: Comentario | L1: Registrado por
A2: 45967.699 | B2: Enero | C2: 1_Stars_Percentage | D2: 3195695 | E2: MartinezS, Sebastian - 5695 | F2: US Spa Earner Acc/Pay | G2: 146115.09 | H2: 10 | I2: 14611.509 | J2: 160726.6 | K2: Ospina, Michel | L2: Activo
A3: 45967.7 | B3: Enero | C3: 1_Stars_Percentage | D3: 3195695 | E3: MartinezS, Sebastian - 5695 | F3: US Spa Earner Acc/Pay | G3: 146115.09 | H3: 10 | I3: 14611.509 | J3: 160726.6 | K3: Ospina, Michel | L3: Activo
A4: 45968.735 | B4: Enero | C4: 1_Stars_Percentage | D4: 3195695 | E4: MartinezS, Sebastian - 5695 | F4: US Spa Earner Acc/Pay | G4: 146115.09 | H4: 30 | I4: 43834.527 | J4: 189949.62 | K4: Ospina, Michel | L4: Activo
A5: 45968.735 | B5: Enero | C5: 1_Stars_Percentage | D5: 3195695 | E5: MartinezS, Sebastian - 5695 | F5: US Spa Earner Acc/Pay | G5: 146115.09 | H5: 30 | I5: 43834.527 | J5: 189949.62 | K5: Ospina, Michel | L5: Activo
A6: 45968.738 | B6: Enero | C6: 1_Stars_Percentage | D6: 5651744 | E6: Ramirez, Erika - 1744 | F6: US Cross Support | G6: 198025.74 | H6: 20 | I6: 39605.148 | J6: 237630.89 | K6: Ospina, Michel | L6: Activo
A7: 45968.751 | B7: Enero | C7: 1_Stars_Percentage | D7: 5651744 | E7: Ramirez, Erika - 1744 | F7: US Cross Support | G7: 198025.74 | H7: 10 | I7: 19802.574 | J7: 217828.31 | K7: Ospina, Michel | L7: Activo
A8: 45968.751 | B8: Enero | C8: 1_Stars_Percentage | D8: 5872088 | E8: Munoz, Marlon - 2088 | F8: US Cross Support | G8: 198025.74 | H8: 30 | I8: 59407.722 | J8: 257433.46 | K8: Ospina, Michel | L8: Activo
A9: 45968.755 | B9: Enero | C9: 1_Stars_Percentage | D9: 3195695 | E9: MartinezS, Sebastian - 5695 | F9: US Spa Earner Acc/Pay | G9: 146115.09 | H9: 10 | I9: 14611.509 | J9: 160726.6 | K9: Ospina, Michel | L9: Activo
A10: 45968.758 | B10: Marzo | C10: ABS Injus | D10: 4747160 | E10: DiazV, Nicolas - 7160 | F10: US Spa Earner Acc/Pay | G10: 0 | H10: 10 | I10: 0 | J10: 0 | K10: Ospina, Michel | L10: Activo
A11: 45969.619 | B11: Enero | C11: Quality@Uber | D11: 5439948 | E11: Moyano, Valeria - 9948 | F11: US Spa Earner Acc/Pay | G11: 97410.06 | H11: 10 | I11: 9741.006 | J11: 107151.07 | K11: Ospina, Michel | L11: Activo
A12: 45969.62 | B12: Enero | C12: Quality@Uber | D12: 3524085 | E12: Gomez, Patricia - 4085 | F12: US Spa Earner Acc/Pay | G12: 97410.06 | H12: 30 | I12: 29223.018 | J12: 126633.08 | K12: Ospina, Michel | L12: Activo
A13: 45970.538 | B13: Enero | C13: 1_Stars_Percentage | D13: 3195695 | E13: MartinezS, Sebastian - 5695 | F13: US Spa Earner Acc/Pay | G13: 146115.09 | H13: 30 | I13: 43834.527 | J13: 189949.62 | K13: Ospina, Michel | L13: Activo
A14: 45970.555 | B14: Enero | C14: 1_Stars_Percentage | D14: 5360362 | E14: Puentes, Anderson - 0362 | F14: US Cross Support | G14: 194820.12 | H14: 30 | I14: 58446.036 | J14: 253266.16 | K14: Ospina, Michel | L14: Activo
A15: 45970.723 | B15: Enero | C15: 1_Stars_Percentage | D15: 3195695 | E15: MartinezS, Sebastian - 5695 | F15: US Spa Earner Acc/Pay | G15: 146115.09 | H15: 10 | I15: 14611.509 | J15: 160726.6 | K15: holaaaaaaaaa | L15: Ospina, Michel | M15: Activo
A16: 45970.724 | B16: Enero | C16: 1_Stars_Percentage | D16: 5546274 | E16: Vargas, Maria - 6274 | F16: US Spa Earner Acc/Pay | G16: 146115.09 | H16: 30 | I16: 43834.527 | J16: 189949.62 | K16: mike | L16: Ospina, Michel | M16: Activo
